{"brains":[{"neurone_web":[{"neurones":[{"x":218.75043061041046,"y":24.701658016812377,"width":20,"height":20,"activation_condition":"Obstacle","activation":"Activate"},{"x":54.42983584987981,"y":137.43142617037705,"width":20,"height":20,"activation_condition":"Obstacle","activation":"PreventActivate"},{"x":935.12705135321,"y":19.979711854193877,"width":20,"height":20,"activation_condition":"Obstacle","activation":"Activate"},{"x":728.9825349814082,"y":238.5277318069309,"width":20,"height":20,"activation_condition":"Obstacle","activation":"Activate"}],"action":"Jump"},{"neurones":[{"x":3.0726254806543767,"y":70.7063380692129,"width":20,"height":20,"activation_condition":"Obstacle","activation":"Activate"},{"x":1241.6375320588895,"y":102.36025899543617,"width":20,"height":20,"activation_condition":"Air","activation":"PreventActivate"}],"action":"Bend"}]},{"neurone_web":[{"neurones":[{"x":203.47684532627952,"y":25.722840545122082,"width":20,"height":20,"activation_condition":"Obstacle","activation":"Activate"},{"x":49.393973432697095,"y":127.20067547987102,"width":20,"height":20,"activation_condition":"Obstacle","activation":"PreventActivate"},{"x":893.0602174602019,"y":15.99620691893976,"width":20,"height":20,"activation_condition":"Obstacle","activation":"Activate"}],"action":"Jump"},{"neurones":[{"x":40.3865386620892,"y":85.53542619948652,"width":20,"height":20,"activation_condition":"Obstacle","activation":"Activate"},{"x":303.56914212292804,"y":262.1506640043473,"width":20,"height":20,"activation_condition":"Obstacle","activation":"Activate"}],"action":"Bend"},{"neurones":[{"x":171.14854672440933,"y":9.652792463877283,"width":20,"height":20,"activation_condition":"Air","activation":"Activate"},{"x":983.5845422496577,"y":80.16826394314948,"width":20,"height":20,"activation_condition":"Air","activation":"Activate"},{"x":452.8624729919061,"y":36.49665985037494,"width":20,"height":20,"activation_condition":"Air","activation":"PreventActivate"}],"action":"Unbend"}]},{"neurone_web":[{"neurones":[{"x":203.9720257643234,"y":14.952991043062639,"width":20,"height":20,"activation_condition":"Obstacle","activation":"Activate"},{"x":93.54649879590815,"y":133.92302838430618,"width":20,"height":20,"activation_condition":"Obstacle","activation":"PreventActivate"},{"x":893.9487716761151,"y":17.26445823906427,"width":20,"height":20,"activation_condition":"Obstacle","activation":"Activate"},{"x":340.26022132202627,"y":186.96109379070228,"width":20,"height":20,"activation_condition":"Obstacle","activation":"Activate"}],"action":"Jump"},{"neurones":[{"x":13.2915786430433,"y":32.254887101083256,"width":20,"height":20,"activation_condition":"Obstacle","activation":"Activate"},{"x":1221.8125601372226,"y":112.5536838049472,"width":20,"height":20,"activation_condition":"Air","activation":"PreventActivate"},{"x":16.859337595782446,"y":542.5894665535604,"width":20,"height":20,"activation_condition":"Obstacle","activation":"Activate"},{"x":466.2991544794264,"y":606.7805482566381,"width":20,"height":20,"activation_condition":"Obstacle","activation":"PreventActivate"}],"action":"Bend"}]},{"neurone_web":[{"neurones":[{"x":216.42413656486258,"y":9.812047890576135,"width":20,"height":20,"activation_condition":"Obstacle","activation":"Activate"},{"x":56.832382070392015,"y":104.0830974184332,"width":20,"height":20,"activation_condition":"Obstacle","activation":"PreventActivate"},{"x":900.7100402529878,"y":36.063427303757514,"width":20,"height":20,"activation_condition":"Obstacle","activation":"Activate"}],"action":"Jump"},{"neurones":[{"x":27.349872373608335,"y":18.610079005653034,"width":20,"height":20,"activation_condition":"Obstacle","activation":"Activate"},{"x":1207.1271272031595,"y":104.0012661126818,"width":20,"height":20,"activation_condition":"Air","activation":"PreventActivate"}],"action":"Bend"},{"neurones":[{"x":439.0105286535091,"y":500.2660707085375,"width":20,"height":20,"activation_condition":"Air","activation":"Activate"},{"x":697.4885784094342,"y":225.04595516435518,"width":20,"height":20,"activation_condition":"Obstacle","activation":"PreventActivate"},{"x":931.8418365606898,"y":651.427660978036,"width":20,"height":20,"activation_condition":"Air","activation":"PreventActivate"}],"action":"Jump"}]},{"neurone_web":[{"neurones":[{"x":227.78528195373167,"y":9.66345823979089,"width":20,"height":20,"activation_condition":"Obstacle","activation":"Activate"},{"x":84.58103280335379,"y":135.0877969196063,"width":20,"height":20,"activation_condition":"Obstacle","activation":"PreventActivate"},{"x":895.8818187798903,"y":34.66196712557752,"width":20,"height":20,"activation_condition":"Obstacle","activation":"Activate"},{"x":723.1786377355374,"y":227.74423189220562,"width":20,"height":20,"activation_condition":"Obstacle","activation":"Activate"}],"action":"Jump"},{"neurones":[{"x":19.794885335233623,"y":37.826664399707795,"width":20,"height":20,"activation_condition":"Obstacle","activation":"Activate"},{"x":1246.8643057817083,"y":110.63072583568879,"width":20,"height":20,"activation_condition":"Air","activation":"PreventActivate"}],"action":"Bend"}]},{"neurone_web":[{"neurones":[{"x":229.70745914217179,"y":17.483093855516728,"width":20,"height":20,"activation_condition":"Obstacle","activation":"Activate"},{"x":68.8307039721255,"y":92.59926054722072,"width":20,"height":20,"activation_condition":"Obstacle","activation":"PreventActivate"},{"x":900.4391538334282,"y":14.503223411977643,"width":20,"height":20,"activation_condition":"Obstacle","activation":"Activate"}],"action":"Jump"},{"neurones":[{"x":64.34818964708639,"y":12.275084818505611,"width":20,"height":20,"activation_condition":"Obstacle","activation":"Activate"},{"x":1199.4681538254956,"y":131.23183111228738,"width":20,"height":20,"activation_condition":"Air","activation":"PreventActivate"},{"x":438.03779026650153,"y":570.2061437293389,"width":20,"height":20,"activation_condition":"Obstacle","activation":"Activate"}],"action":"Bend"},{"neurones":[{"x":866.6462334873663,"y":535.5713325787088,"width":20,"height":20,"activation_condition":"Obstacle","activation":"PreventActivate"},{"x":217.5872875763338,"y":102.47298506283225,"width":20,"height":20,"activation_condition":"Air","activation":"PreventActivate"}],"action":"Bend"}]},{"neurone_web":[{"neurones":[{"x":179.60659574740413,"y":20.201198514595823,"width":20,"height":20,"activation_condition":"Obstacle","activation":"Activate"},{"x":58.69158106397099,"y":140.32833999436485,"width":20,"height":20,"activation_condition":"Obstacle","activation":"PreventActivate"},{"x":903.0716603562627,"y":16.421308644918586,"width":20,"height":20,"activation_condition":"Obstacle","activation":"Activate"}],"action":"Jump"},{"neurones":[{"x":2.522472491044351,"y":18.59490609446295,"width":20,"height":20,"activation_condition":"Obstacle","activation":"Activate"},{"x":1214.2705140044668,"y":97.47533264506154,"width":20,"height":20,"activation_condition":"Air","activation":"PreventActivate"}],"action":"Bend"}]},{"neurone_web":[{"neurones":[{"x":251.78724791711898,"y":19.875459009724462,"width":20,"height":20,"activation_condition":"Obstacle","activation":"Activate"},{"x":72.88904279393444,"y":96.54939709895528,"width":20,"height":20,"activation_condition":"Obstacle","activation":"PreventActivate"},{"x":896.637403929922,"y":19.117921892619897,"width":20,"height":20,"activation_condition":"Obstacle","activation":"Activate"}],"action":"Jump"},{"neurones":[{"x":70.13609978716556,"y":36.28191351508854,"width":20,"height":20,"activation_condition":"Obstacle","activation":"Activate"},{"x":1222.9348020213083,"y":129.4775830428734,"width":20,"height":20,"activation_condition":"Air","activation":"PreventActivate"},{"x":109.34878329932609,"y":295.6088518245874,"width":20,"height":20,"activation_condition":"Obstacle","activation":"PreventActivate"}],"action":"Bend"}]},{"neurone_web":[{"neurones":[{"x":233.23823457396884,"y":32.492432691706426,"width":20,"height":20,"activation_condition":"Obstacle","activation":"Activate"},{"x":47.975442832119775,"y":149.00984950659625,"width":20,"height":20,"activation_condition":"Obstacle","activation":"PreventActivate"},{"x":918.548938272663,"y":13.360053034607487,"width":20,"height":20,"activation_condition":"Obstacle","activation":"Activate"},{"x":1149.8122186433234,"y":624.513604139699,"width":20,"height":20,"activation_condition":"Obstacle","activation":"PreventActivate"}],"action":"Jump"},{"neurones":[{"x":74.83135864540529,"y":20.13392889864856,"width":20,"height":20,"activation_condition":"Obstacle","activation":"Activate"},{"x":1204.7131622368822,"y":139.37643257516905,"width":20,"height":20,"activation_condition":"Air","activation":"PreventActivate"}],"action":"Bend"}]},{"neurone_web":[{"neurones":[{"x":219.50918470113396,"y":21.155074537904262,"width":20,"height":20,"activation_condition":"Obstacle","activation":"Activate"},{"x":58.54418826102658,"y":144.24182821744006,"width":20,"height":20,"activation_condition":"Obstacle","activation":"PreventActivate"},{"x":910.6379759425855,"y":21.37115129212539,"width":20,"height":20,"activation_condition":"Obstacle","activation":"Activate"},{"x":1102.3024165153877,"y":436.0452353724853,"width":20,"height":20,"activation_condition":"Obstacle","activation":"Activate"},{"x":455.9324331220379,"y":105.20560813161786,"width":20,"height":20,"activation_condition":"Obstacle","activation":"PreventActivate"}],"action":"Jump"},{"neurones":[{"x":30.591468067763174,"y":28.91999652399772,"width":20,"height":20,"activation_condition":"Obstacle","activation":"Activate"},{"x":1161.478660710825,"y":100.83877543778134,"width":20,"height":20,"activation_condition":"Air","activation":"PreventActivate"}],"action":"Bend"}]},{"neurone_web":[{"neurones":[{"x":208.42319178502393,"y":18.961732330892985,"width":20,"height":20,"activation_condition":"Obstacle","activation":"Activate"},{"x":46.92466104357126,"y":96.77735987525315,"width":20,"height":20,"activation_condition":"Obstacle","activation":"PreventActivate"},{"x":936.0656129259593,"y":35.18557182616984,"width":20,"height":20,"activation_condition":"Obstacle","activation":"Activate"},{"x":719.1197793110235,"y":381.046792304925,"width":20,"height":20,"activation_condition":"Obstacle","activation":"PreventActivate"},{"x":1212.6064351758719,"y":389.0573167142272,"width":20,"height":20,"activation_condition":"Obstacle","activation":"PreventActivate"}],"action":"Jump"},{"neurones":[{"x":14.968573039405355,"y":55.715828130122866,"width":20,"height":20,"activation_condition":"Obstacle","activation":"Activate"},{"x":1200.6561296480663,"y":90.30619643776262,"width":20,"height":20,"activation_condition":"Air","activation":"PreventActivate"}],"action":"Bend"},{"neurones":[{"x":550.2028390395739,"y":331.66620575554566,"width":20,"height":20,"activation_condition":"Obstacle","activation":"Activate"}],"action":"Unbend"}]},{"neurone_web":[{"neurones":[{"x":180.06717955745017,"y":27.58246758162886,"width":20,"height":20,"activation_condition":"Obstacle","activation":"Activate"},{"x":72.86329093015237,"y":108.81544880777312,"width":20,"height":20,"activation_condition":"Obstacle","activation":"PreventActivate"},{"x":892.7355104835253,"y":20.01619740757317,"width":20,"height":20,"activation_condition":"Obstacle","activation":"Activate"}],"action":"Jump"},{"neurones":[{"x":60.41391851869638,"y":61.83089245877046,"width":20,"height":20,"activation_condition":"Obstacle","activation":"Activate"},{"x":1205.9027478252833,"y":108.2465990613695,"width":20,"height":20,"activation_condition":"Air","activation":"PreventActivate"},{"x":925.5467426375645,"y":168.04012263219894,"width":20,"height":20,"activation_condition":"Obstacle","activation":"PreventActivate"}],"action":"Bend"},{"neurones":[{"x":805.3635147825146,"y":484.1391575862303,"width":20,"height":20,"activation_condition":"Air","activation":"PreventActivate"},{"x":542.2295987693946,"y":482.7362036016431,"width":20,"height":20,"activation_condition":"Obstacle","activation":"PreventActivate"},{"x":1224.2306606710235,"y":517.1464172343619,"width":20,"height":20,"activation_condition":"Obstacle","activation":"PreventActivate"}],"action":"Unbend"},{"neurones":[{"x":374.04180065542147,"y":612.4471367093123,"width":20,"height":20,"activation_condition":"Air","activation":"PreventActivate"},{"x":748.2540184192052,"y":699.6647599043697,"width":20,"height":20,"activation_condition":"Air","activation":"PreventActivate"},{"x":821.5951739358676,"y":216.6811903992931,"width":20,"height":20,"activation_condition":"Air","activation":"PreventActivate"}],"action":"Unbend"}]},{"neurone_web":[{"neurones":[{"x":240.20058781428088,"y":26.57211004481593,"width":20,"height":20,"activation_condition":"Obstacle","activation":"Activate"},{"x":55.266840260918116,"y":129.03142799195373,"width":20,"height":20,"activation_condition":"Obstacle","activation":"PreventActivate"},{"x":910.3269735290776,"y":32.163811519455635,"width":20,"height":20,"activation_condition":"Obstacle","activation":"Activate"},{"x":723.0394612287412,"y":575.5375094406197,"width":20,"height":20,"activation_condition":"Obstacle","activation":"PreventActivate"}],"action":"Jump"},{"neurones":[{"x":23.175242027760927,"y":62.471508940666844,"width":20,"height":20,"activation_condition":"Obstacle","activation":"Activate"},{"x":1221.9365729792607,"y":146.35303197747132,"width":20,"height":20,"activation_condition":"Air","activation":"PreventActivate"}],"action":"Bend"}]},{"neurone_web":[{"neurones":[{"x":171.82209506900054,"y":9.67754423331122,"width":20,"height":20,"activation_condition":"Obstacle","activation":"Activate"},{"x":59.154389235732836,"y":99.88649276691739,"width":20,"height":20,"activation_condition":"Obstacle","activation":"PreventActivate"},{"x":945.4254730653025,"y":17.966531424443346,"width":20,"height":20,"activation_condition":"Obstacle","activation":"Activate"}],"action":"Jump"},{"neurones":[{"x":25.992921782174868,"y":33.401273884459535,"width":20,"height":20,"activation_condition":"Obstacle","activation":"Activate"},{"x":1210.5540311508505,"y":96.9366408311621,"width":20,"height":20,"activation_condition":"Air","activation":"PreventActivate"}],"action":"Bend"},{"neurones":[{"x":1165.5860621154084,"y":357.486690792715,"width":20,"height":20,"activation_condition":"Air","activation":"PreventActivate"},{"x":117.51465810588563,"y":240.8390298154842,"width":20,"height":20,"activation_condition":"Obstacle","activation":"PreventActivate"},{"x":248.51840513813684,"y":409.162678961126,"width":20,"height":20,"activation_condition":"Air","activation":"Activate"}],"action":"Jump"},{"neurones":[{"x":338.4052063427344,"y":189.30221446612993,"width":20,"height":20,"activation_condition":"Air","activation":"PreventActivate"},{"x":197.926527314503,"y":463.5859507183853,"width":20,"height":20,"activation_condition":"Obstacle","activation":"Activate"},{"x":482.0966858774897,"y":121.71403034065604,"width":20,"height":20,"activation_condition":"Obstacle","activation":"Activate"},{"x":997.3461194661812,"y":272.0315001195796,"width":20,"height":20,"activation_condition":"Air","activation":"Activate"},{"x":711.8040696555141,"y":513.7392679369989,"width":20,"height":20,"activation_condition":"Air","activation":"PreventActivate"}],"action":"Jump"}]},{"neurone_web":[{"neurones":[{"x":186.63296938010023,"y":28.608936906609266,"width":20,"height":20,"activation_condition":"Obstacle","activation":"Activate"},{"x":80.93612502510356,"y":92.39036607260942,"width":20,"height":20,"activation_condition":"Obstacle","activation":"PreventActivate"},{"x":903.8853836140854,"y":17.521865910951405,"width":20,"height":20,"activation_condition":"Obstacle","activation":"Activate"}],"action":"Jump"},{"neurones":[{"x":73.49187502182855,"y":79.4158435581619,"width":20,"height":20,"activation_condition":"Obstacle","activation":"Activate"},{"x":1232.803186832277,"y":125.95423956410266,"width":20,"height":20,"activation_condition":"Air","activation":"PreventActivate"}],"action":"Bend"},{"neurones":[{"x":478.17547329152626,"y":561.9326888133228,"width":20,"height":20,"activation_condition":"Obstacle","activation":"Activate"}],"action":"Unbend"}]},{"neurone_web":[{"neurones":[{"x":250.04682532369844,"y":37.13689558502726,"width":20,"height":20,"activation_condition":"Obstacle","activation":"Activate"},{"x":95.72229772213947,"y":96.646754705569,"width":20,"height":20,"activation_condition":"Obstacle","activation":"PreventActivate"},{"x":904.220583289745,"y":26.79415623863039,"width":20,"height":20,"activation_condition":"Obstacle","activation":"Activate"}],"action":"Jump"},{"neurones":[{"x":31.875451548856066,"y":46.9171997710317,"width":20,"height":20,"activation_condition":"Obstacle","activation":"Activate"},{"x":1228.4061130514278,"y":139.62284045687915,"width":20,"height":20,"activation_condition":"Air","activation":"PreventActivate"},{"x":489.7985247164456,"y":660.4834546207348,"width":20,"height":20,"activation_condition":"Obstacle","activation":"Activate"}],"action":"Bend"}]},{"neurone_web":[{"neurones":[{"x":202.6656524910944,"y":12.352431148911286,"width":20,"height":20,"activation_condition":"Obstacle","activation":"Activate"},{"x":71.07112925342707,"y":105.64213395087079,"width":20,"height":20,"activation_condition":"Obstacle","activation":"PreventActivate"},{"x":893.6098755296377,"y":15.927426181098744,"width":20,"height":20,"activation_condition":"Obstacle","activation":"Activate"}],"action":"Jump"},{"neurones":[{"x":66.94336137079864,"y":67.01614261521593,"width":20,"height":20,"activation_condition":"Obstacle","activation":"Activate"},{"x":1230.9193778331833,"y":124.04478779755152,"width":20,"height":20,"activation_condition":"Air","activation":"PreventActivate"},{"x":417.11055764049615,"y":553.01354008892,"width":20,"height":20,"activation_condition":"Obstacle","activation":"Activate"}],"action":"Bend"},{"neurones":[{"x":685.0711560420904,"y":32.00319731180593,"width":20,"height":20,"activation_condition":"Air","activation":"PreventActivate"},{"x":317.6147745222472,"y":391.5844855144945,"width":20,"height":20,"activation_condition":"Obstacle","activation":"PreventActivate"},{"x":109.4125101240123,"y":488.4679047675874,"width":20,"height":20,"activation_condition":"Air","activation":"PreventActivate"}],"action":"Unbend"}]},{"neurone_web":[{"neurones":[{"x":234.2050882406812,"y":9.718694832337619,"width":20,"height":20,"activation_condition":"Obstacle","activation":"Activate"},{"x":92.82886170567392,"y":122.13764122109498,"width":20,"height":20,"activation_condition":"Obstacle","activation":"PreventActivate"},{"x":893.7490045155378,"y":8.886128482327756,"width":20,"height":20,"activation_condition":"Obstacle","activation":"Activate"},{"x":481.91198660773614,"y":12.501786864925318,"width":20,"height":20,"activation_condition":"Obstacle","activation":"PreventActivate"},{"x":1023.7904279365854,"y":168.11836679283596,"width":20,"height":20,"activation_condition":"Obstacle","activation":"PreventActivate"}],"action":"Jump"},{"neurones":[{"x":12.15256379608547,"y":85.3146992215978,"width":20,"height":20,"activation_condition":"Obstacle","activation":"Activate"},{"x":1195.820344296287,"y":109.0645030444484,"width":20,"height":20,"activation_condition":"Air","activation":"PreventActivate"}],"action":"Bend"}]},{"neurone_web":[{"neurones":[{"x":236.87909985083425,"y":27.64905432693807,"width":20,"height":20,"activation_condition":"Obstacle","activation":"Activate"},{"x":58.53237285370628,"y":146.3845178504135,"width":20,"height":20,"activation_condition":"Obstacle","activation":"PreventActivate"},{"x":928.9281665178512,"y":22.95657101256338,"width":20,"height":20,"activation_condition":"Obstacle","activation":"Activate"}],"action":"Jump"},{"neurones":[{"x":80.57570094736634,"y":30.28193089486277,"width":20,"height":20,"activation_condition":"Obstacle","activation":"Activate"},{"x":1253.3247812459913,"y":121.69772101470453,"width":20,"height":20,"activation_condition":"Air","activation":"PreventActivate"}],"action":"Bend"},{"neurones":[{"x":1258.4011034693683,"y":185.13729113325496,"width":20,"height":20,"activation_condition":"Air","activation":"PreventActivate"},{"x":246.36890893783058,"y":188.5494779004692,"width":20,"height":20,"activation_condition":"Air","activation":"PreventActivate"},{"x":594.899351129068,"y":211.70861021986616,"width":20,"height":20,"activation_condition":"Air","activation":"PreventActivate"},{"x":1179.4982270789517,"y":296.5251425605428,"width":20,"height":20,"activation_condition":"Air","activation":"Activate"}],"action":"Jump"}]},{"neurone_web":[{"neurones":[{"x":224.42190561744206,"y":34.797858121384834,"width":20,"height":20,"activation_condition":"Obstacle","activation":"Activate"},{"x":49.672884575569455,"y":113.18398842689544,"width":20,"height":20,"activation_condition":"Obstacle","activation":"PreventActivate"},{"x":895.234275105906,"y":22.28339971219549,"width":20,"height":20,"activation_condition":"Obstacle","activation":"Activate"},{"x":272.02342203812856,"y":645.2929881908833,"width":20,"height":20,"activation_condition":"Obstacle","activation":"PreventActivate"}],"action":"Jump"},{"neurones":[{"x":52.35243454100713,"y":95.22454339131896,"width":20,"height":20,"activation_condition":"Obstacle","activation":"Activate"},{"x":1207.2137259614885,"y":116.6259321059892,"width":20,"height":20,"activation_condition":"Air","activation":"PreventActivate"}],"action":"Bend"}]},{"neurone_web":[{"neurones":[{"x":241.70024257961097,"y":8.054291270981572,"width":20,"height":20,"activation_condition":"Obstacle","activation":"Activate"},{"x":97.76054183711838,"y":126.20805150059137,"width":20,"height":20,"activation_condition":"Obstacle","activation":"PreventActivate"},{"x":902.1567950385252,"y":17.881365327260514,"width":20,"height":20,"activation_condition":"Obstacle","activation":"Activate"}],"action":"Jump"},{"neurones":[{"x":85.0824719477468,"y":9.55998482351662,"width":20,"height":20,"activation_condition":"Obstacle","activation":"Activate"},{"x":1234.6432126572838,"y":137.33755829434787,"width":20,"height":20,"activation_condition":"Air","activation":"PreventActivate"},{"x":1046.771396946138,"y":211.93413747555357,"width":20,"height":20,"activation_condition":"Obstacle","activation":"Activate"}],"action":"Bend"},{"neurones":[{"x":1018.1882609114841,"y":244.2745371074642,"width":20,"height":20,"activation_condition":"Air","activation":"PreventActivate"},{"x":370.16693985289646,"y":305.5770328818896,"width":20,"height":20,"activation_condition":"Air","activation":"Activate"},{"x":864.0738056722021,"y":30.636166948538225,"width":20,"height":20,"activation_condition":"Air","activation":"Activate"},{"x":1053.1667814581876,"y":673.8173764013819,"width":20,"height":20,"activation_condition":"Obstacle","activation":"Activate"}],"action":"Jump"}]},{"neurone_web":[{"neurones":[{"x":192.22895380301188,"y":12.984391254979949,"width":20,"height":20,"activation_condition":"Obstacle","activation":"Activate"},{"x":51.1161550387902,"y":119.1405463733148,"width":20,"height":20,"activation_condition":"Obstacle","activation":"PreventActivate"},{"x":908.3522489423876,"y":8.91139392437512,"width":20,"height":20,"activation_condition":"Obstacle","activation":"Activate"}],"action":"Jump"},{"neurones":[{"x":28.482548273998052,"y":25.832319609171403,"width":20,"height":20,"activation_condition":"Obstacle","activation":"Activate"},{"x":1192.4395324294649,"y":142.24596306662914,"width":20,"height":20,"activation_condition":"Air","activation":"PreventActivate"},{"x":770.6918733583705,"y":648.4649850250031,"width":20,"height":20,"activation_condition":"Obstacle","activation":"PreventActivate"}],"action":"Bend"},{"neurones":[{"x":37.21328515586458,"y":268.96487374497127,"width":20,"height":20,"activation_condition":"Air","activation":"PreventActivate"},{"x":408.2235433246714,"y":168.76245626316515,"width":20,"height":20,"activation_condition":"Air","activation":"Activate"},{"x":220.3023620082887,"y":581.9316853887766,"width":20,"height":20,"activation_condition":"Obstacle","activation":"PreventActivate"}],"action":"Unbend"}]},{"neurone_web":[{"neurones":[{"x":229.19896389590136,"y":33.95982568012572,"width":20,"height":20,"activation_condition":"Obstacle","activation":"Activate"},{"x":81.7412468814124,"y":101.45234013365204,"width":20,"height":20,"activation_condition":"Obstacle","activation":"PreventActivate"},{"x":891.8740572584561,"y":35.14153602629208,"width":20,"height":20,"activation_condition":"Obstacle","activation":"Activate"}],"action":"Jump"},{"neurones":[{"x":22.053128415989832,"y":42.970998172465734,"width":20,"height":20,"activation_condition":"Obstacle","activation":"Activate"},{"x":1205.387188870837,"y":132.0898922398362,"width":20,"height":20,"activation_condition":"Air","activation":"PreventActivate"}],"action":"Bend"}]},{"neurone_web":[{"neurones":[{"x":204.1806041511884,"y":33.24934504996938,"width":20,"height":20,"activation_condition":"Obstacle","activation":"Activate"},{"x":56.94111337668534,"y":140.19585798601742,"width":20,"height":20,"activation_condition":"Obstacle","activation":"PreventActivate"},{"x":915.6744230034368,"y":26.145707827697294,"width":20,"height":20,"activation_condition":"Obstacle","activation":"Activate"},{"x":966.6222448971971,"y":612.6191041858992,"width":20,"height":20,"activation_condition":"Obstacle","activation":"PreventActivate"}],"action":"Jump"},{"neurones":[{"x":70.39487775060181,"y":85.89244466310245,"width":20,"height":20,"activation_condition":"Obstacle","activation":"Activate"},{"x":1248.1082790670266,"y":100.0670754948448,"width":20,"height":20,"activation_condition":"Air","activation":"PreventActivate"},{"x":67.94299278515854,"y":186.7116258116394,"width":20,"height":20,"activation_condition":"Obstacle","activation":"PreventActivate"}],"action":"Bend"},{"neurones":[{"x":204.03473828491428,"y":99.05052933321689,"width":20,"height":20,"activation_condition":"Air","activation":"Activate"},{"x":554.9400471191132,"y":290.1213940143406,"width":20,"height":20,"activation_condition":"Air","activation":"PreventActivate"}],"action":"Unbend"}]},{"neurone_web":[{"neurones":[{"x":256.6106785794833,"y":23.69090811599656,"width":20,"height":20,"activation_condition":"Obstacle","activation":"Activate"},{"x":136.42850959229708,"y":92.30058531241309,"width":20,"height":20,"activation_condition":"Obstacle","activation":"PreventActivate"},{"x":902.8498717588309,"y":26.98476926917143,"width":20,"height":20,"activation_condition":"Obstacle","activation":"Activate"},{"x":49.29438323524194,"y":362.40025429425054,"width":20,"height":20,"activation_condition":"Obstacle","activation":"Activate"}],"action":"Jump"},{"neurones":[{"x":12.40308980759804,"y":74.18134092705549,"width":20,"height":20,"activation_condition":"Obstacle","activation":"Activate"},{"x":1244.8373706057046,"y":96.9850301534376,"width":20,"height":20,"activation_condition":"Air","activation":"PreventActivate"}],"action":"Bend"},{"neurones":[{"x":343.00276613758047,"y":221.44899250003195,"width":20,"height":20,"activation_condition":"Air","activation":"PreventActivate"},{"x":199.20101764847456,"y":508.7738451197575,"width":20,"height":20,"activation_condition":"Air","activation":"PreventActivate"},{"x":1232.8697973440492,"y":386.1051586311695,"width":20,"height":20,"activation_condition":"Air","activation":"Activate"},{"x":608.7075580880364,"y":158.94184634369535,"width":20,"height":20,"activation_condition":"Air","activation":"PreventActivate"},{"x":997.9324554372074,"y":484.17902249912015,"width":20,"height":20,"activation_condition":"Obstacle","activation":"Activate"}],"action":"Unbend"}]},{"neurone_web":[{"neurones":[{"x":222.38672764388465,"y":17.017929408649742,"width":20,"height":20,"activation_condition":"Obstacle","activation":"Activate"},{"x":80.97161267497316,"y":118.41890491072535,"width":20,"height":20,"activation_condition":"Obstacle","activation":"PreventActivate"},{"x":903.0108478733669,"y":29.474619636452545,"width":20,"height":20,"activation_condition":"Obstacle","activation":"Activate"},{"x":72.3215862341181,"y":80.40703795485764,"width":20,"height":20,"activation_condition":"Obstacle","activation":"Activate"}],"action":"Jump"},{"neurones":[{"x":23.44869128396239,"y":92.33291001189976,"width":20,"height":20,"activation_condition":"Obstacle","activation":"Activate"},{"x":1255.1233690469203,"y":108.10713665833262,"width":20,"height":20,"activation_condition":"Air","activation":"PreventActivate"},{"x":415.49286272225777,"y":535.5720597639857,"width":20,"height":20,"activation_condition":"Obstacle","activation":"Activate"}],"action":"Bend"}]},{"neurone_web":[{"neurones":[{"x":189.35309217361342,"y":25.3321249121367,"width":20,"height":20,"activation_condition":"Obstacle","activation":"Activate"},{"x":48.814934715757765,"y":121.60290634931911,"width":20,"height":20,"activation_condition":"Obstacle","activation":"PreventActivate"},{"x":909.9414353554872,"y":39.16970136032322,"width":20,"height":20,"activation_condition":"Obstacle","activation":"Activate"}],"action":"Jump"},{"neurones":[{"x":5.237234992469307,"y":73.80565364820616,"width":20,"height":20,"activation_condition":"Obstacle","activation":"Activate"},{"x":1208.2656348723494,"y":147.26176809285136,"width":20,"height":20,"activation_condition":"Air","activation":"PreventActivate"}],"action":"Bend"}]},{"neurone_web":[{"neurones":[{"x":224.35608426108536,"y":30.878781637013304,"width":20,"height":20,"activation_condition":"Obstacle","activation":"Activate"},{"x":70.91920015586695,"y":117.6159532020498,"width":20,"height":20,"activation_condition":"Obstacle","activation":"PreventActivate"},{"x":894.6425075657265,"y":12.487654860718154,"width":20,"height":20,"activation_condition":"Obstacle","activation":"Activate"}],"action":"Jump"},{"neurones":[{"x":13.536113946067802,"y":53.446745173559314,"width":20,"height":20,"activation_condition":"Obstacle","activation":"Activate"},{"x":1259.4778044517607,"y":131.98019794265036,"width":20,"height":20,"activation_condition":"Air","activation":"PreventActivate"}],"action":"Bend"}]},{"neurone_web":[{"neurones":[{"x":193.2651387569518,"y":11.608803586182653,"width":20,"height":20,"activation_condition":"Obstacle","activation":"Activate"},{"x":85.56491280532617,"y":117.27040413795527,"width":20,"height":20,"activation_condition":"Obstacle","activation":"PreventActivate"},{"x":893.1637944588113,"y":21.43899287739726,"width":20,"height":20,"activation_condition":"Obstacle","activation":"Activate"}],"action":"Jump"},{"neurones":[{"x":102.70376885843484,"y":29.771198333019374,"width":20,"height":20,"activation_condition":"Obstacle","activation":"Activate"},{"x":1227.2594945391813,"y":115.79770018657548,"width":20,"height":20,"activation_condition":"Air","activation":"PreventActivate"},{"x":958.5708067736251,"y":166.49205848824414,"width":20,"height":20,"activation_condition":"Obstacle","activation":"PreventActivate"}],"action":"Bend"},{"neurones":[{"x":818.2165909490357,"y":492.4845149194506,"width":20,"height":20,"activation_condition":"Air","activation":"PreventActivate"},{"x":573.3300937302395,"y":487.7131971071537,"width":20,"height":20,"activation_condition":"Obstacle","activation":"PreventActivate"},{"x":1001.7191870156639,"y":113.09868115111612,"width":20,"height":20,"activation_condition":"Air","activation":"PreventActivate"},{"x":1093.6054963622378,"y":178.1997307733971,"width":20,"height":20,"activation_condition":"Air","activation":"Activate"},{"x":1215.7072254506868,"y":544.1199749206138,"width":20,"height":20,"activation_condition":"Obstacle","activation":"PreventActivate"}],"action":"Unbend"},{"neurones":[{"x":355.5235378946144,"y":605.3725270520329,"width":20,"height":20,"activation_condition":"Air","activation":"PreventActivate"},{"x":788.0248149161068,"y":699.6958507983865,"width":20,"height":20,"activation_condition":"Air","activation":"PreventActivate"},{"x":307.5675356932413,"y":82.18224948428775,"width":20,"height":20,"activation_condition":"Air","activation":"PreventActivate"},{"x":852.1442730621982,"y":218.98638849361092,"width":20,"height":20,"activation_condition":"Air","activation":"PreventActivate"},{"x":1105.0809112720776,"y":126.95581724593573,"width":20,"height":20,"activation_condition":"Obstacle","activation":"Activate"}],"action":"Unbend"}]},{"neurone_web":[{"neurones":[{"x":215.94342746230853,"y":36.04343038185779,"width":20,"height":20,"activation_condition":"Obstacle","activation":"Activate"},{"x":54.733751185925335,"y":149.68809777264457,"width":20,"height":20,"activation_condition":"Obstacle","activation":"PreventActivate"},{"x":920.6802553315812,"y":27.19156824479838,"width":20,"height":20,"activation_condition":"Obstacle","activation":"Activate"}],"action":"Jump"},{"neurones":[{"x":3.1300216920294064,"y":37.69057716674211,"width":20,"height":20,"activation_condition":"Obstacle","activation":"Activate"},{"x":1255.2527426697077,"y":92.60086770624142,"width":20,"height":20,"activation_condition":"Air","activation":"PreventActivate"},{"x":517.0070428550421,"y":650.7161951910934,"width":20,"height":20,"activation_condition":"Obstacle","activation":"Activate"},{"x":34.55831024772953,"y":513.8967713028584,"width":20,"height":20,"activation_condition":"Obstacle","activation":"Activate"},{"x":489.10316215417896,"y":609.9882411076782,"width":20,"height":20,"activation_condition":"Obstacle","activation":"PreventActivate"}],"action":"Bend"},{"neurones":[{"x":742.7133584905263,"y":120.33742278046883,"width":20,"height":20,"activation_condition":"Air","activation":"Activate"},{"x":432.7507303244808,"y":103.96486841637766,"width":20,"height":20,"activation_condition":"Air","activation":"Activate"},{"x":407.82494729805086,"y":247.41261525791566,"width":20,"height":20,"activation_condition":"Air","activation":"PreventActivate"}],"action":"Bend"}]},{"neurone_web":[{"neurones":[{"x":233.59692203267278,"y":7.697625667509542,"width":20,"height":20,"activation_condition":"Obstacle","activation":"Activate"},{"x":51.66560765640847,"y":133.81054736459527,"width":20,"height":20,"activation_condition":"Obstacle","activation":"PreventActivate"},{"x":916.1229439000085,"y":28.59835344999503,"width":20,"height":20,"activation_condition":"Obstacle","activation":"Activate"}],"action":"Jump"},{"neurones":[{"x":2.4803845452385382,"y":19.62894784919642,"width":20,"height":20,"activation_condition":"Obstacle","activation":"Activate"},{"x":1232.4946995083494,"y":137.57959529769323,"width":20,"height":20,"activation_condition":"Air","activation":"PreventActivate"},{"x":750.8225722968525,"y":661.7425751313426,"width":20,"height":20,"activation_condition":"Obstacle","activation":"PreventActivate"},{"x":1136.6887934261451,"y":148.6332688601313,"width":20,"height":20,"activation_condition":"Air","activation":"PreventActivate"}],"action":"Bend"}]},{"neurone_web":[{"neurones":[{"x":219.245984515916,"y":8.556643168436025,"width":20,"height":20,"activation_condition":"Obstacle","activation":"Activate"},{"x":68.65253523269054,"y":106.19231582891962,"width":20,"height":20,"activation_condition":"Obstacle","activation":"PreventActivate"},{"x":893.3926851876939,"y":20.883057571069806,"width":20,"height":20,"activation_condition":"Obstacle","activation":"Activate"},{"x":547.6679170463542,"y":507.49514262341955,"width":20,"height":20,"activation_condition":"Obstacle","activation":"Activate"}],"action":"Jump"},{"neurones":[{"x":21.015537098645577,"y":22.123721874553855,"width":20,"height":20,"activation_condition":"Obstacle","activation":"Activate"},{"x":1177.0616753807142,"y":135.95813204197066,"width":20,"height":20,"activation_condition":"Air","activation":"PreventActivate"}],"action":"Bend"},{"neurones":[{"x":818.3412203708757,"y":563.3101567551257,"width":20,"height":20,"activation_condition":"Obstacle","activation":"PreventActivate"},{"x":441.7093901435553,"y":179.69766654435006,"width":20,"height":20,"activation_condition":"Air","activation":"PreventActivate"},{"x":248.2468710755551,"y":55.959568905241504,"width":20,"height":20,"activation_condition":"Air","activation":"PreventActivate"},{"x":331.8534993888124,"y":245.48127762225283,"width":20,"height":20,"activation_condition":"Obstacle","activation":"PreventActivate"}],"action":"Bend"}]},{"neurone_web":[{"neurones":[{"x":207.05654060055636,"y":36.71693636243806,"width":20,"height":20,"activation_condition":"Obstacle","activation":"Activate"},{"x":54.73051141448749,"y":137.46853462804984,"width":20,"height":20,"activation_condition":"Obstacle","activation":"PreventActivate"},{"x":918.3797010001967,"y":21.07313486081626,"width":20,"height":20,"activation_condition":"Obstacle","activation":"Activate"}],"action":"Jump"},{"neurones":[{"x":1.6496760641858523,"y":74.15990516254841,"width":20,"height":20,"activation_condition":"Obstacle","activation":"Activate"},{"x":1195.6315788418092,"y":134.34080222142563,"width":20,"height":20,"activation_condition":"Air","activation":"PreventActivate"},{"x":773.8734079252118,"y":615.6036330958597,"width":20,"height":20,"activation_condition":"Obstacle","activation":"PreventActivate"}],"action":"Bend"},{"neurones":[{"x":63.26460863158753,"y":310.13881342524166,"width":20,"height":20,"activation_condition":"Air","activation":"PreventActivate"},{"x":414.9191586139703,"y":190.2445161752446,"width":20,"height":20,"activation_condition":"Air","activation":"Activate"},{"x":264.19142431492133,"y":619.9903638595358,"width":20,"height":20,"activation_condition":"Obstacle","activation":"PreventActivate"}],"action":"Unbend"}]},{"neurone_web":[{"neurones":[{"x":197.63018576482747,"y":24.050142827234126,"width":20,"height":20,"activation_condition":"Obstacle","activation":"Activate"},{"x":48.464667537394895,"y":141.7691756324568,"width":20,"height":20,"activation_condition":"Obstacle","activation":"PreventActivate"},{"x":941.011176807965,"y":28.763621250518753,"width":20,"height":20,"activation_condition":"Obstacle","activation":"Activate"}],"action":"Jump"},{"neurones":[{"x":50.91463467245689,"y":43.709659411506976,"width":20,"height":20,"activation_condition":"Obstacle","activation":"Activate"},{"x":1226.2911984178138,"y":141.60413295933733,"width":20,"height":20,"activation_condition":"Air","activation":"PreventActivate"},{"x":730.0333459371541,"y":488.1761203503396,"width":20,"height":20,"activation_condition":"Obstacle","activation":"PreventActivate"}],"action":"Bend"},{"neurones":[{"x":1144.1636959307866,"y":325.10671490861745,"width":20,"height":20,"activation_condition":"Air","activation":"PreventActivate"},{"x":915.275213926023,"y":399.9272907497745,"width":20,"height":20,"activation_condition":"Obstacle","activation":"Activate"},{"x":157.74280833195618,"y":206.617535273968,"width":20,"height":20,"activation_condition":"Obstacle","activation":"PreventActivate"}],"action":"Jump"}]},{"neurone_web":[{"neurones":[{"x":206.25466821587992,"y":16.29765835724624,"width":20,"height":20,"activation_condition":"Obstacle","activation":"Activate"},{"x":79.48100182912059,"y":144.4182675930204,"width":20,"height":20,"activation_condition":"Obstacle","activation":"PreventActivate"},{"x":893.7107260876611,"y":12.639226273162894,"width":20,"height":20,"activation_condition":"Obstacle","activation":"Activate"}],"action":"Jump"},{"neurones":[{"x":51.726734489154566,"y":56.712650856048214,"width":20,"height":20,"activation_condition":"Obstacle","activation":"Activate"},{"x":1188.8395029820722,"y":114.91586679871241,"width":20,"height":20,"activation_condition":"Air","activation":"PreventActivate"},{"x":966.2957520525863,"y":76.7201470722569,"width":20,"height":20,"activation_condition":"Obstacle","activation":"PreventActivate"}],"action":"Bend"},{"neurones":[{"x":795.0305425746989,"y":679.545129762937,"width":20,"height":20,"activation_condition":"Air","activation":"PreventActivate"},{"x":373.1711381131417,"y":668.1488226403036,"width":20,"height":20,"activation_condition":"Air","activation":"Activate"},{"x":1161.6868296411124,"y":601.2941326081475,"width":20,"height":20,"activation_condition":"Obstacle","activation":"PreventActivate"},{"x":1186.725686652621,"y":400.75767513958004,"width":20,"height":20,"activation_condition":"Obstacle","activation":"PreventActivate"},{"x":703.8462190248785,"y":663.620715892243,"width":20,"height":20,"activation_condition":"Obstacle","activation":"Activate"}],"action":"Bend"}]},{"neurone_web":[{"neurones":[{"x":201.1652738106774,"y":27.32029129804909,"width":20,"height":20,"activation_condition":"Obstacle","activation":"Activate"},{"x":94.52443586839459,"y":129.64273812632834,"width":20,"height":20,"activation_condition":"Obstacle","activation":"PreventActivate"},{"x":891.7896228362396,"y":11.673148871812991,"width":20,"height":20,"activation_condition":"Obstacle","activation":"Activate"}],"action":"Jump"},{"neurones":[{"x":11.340701836806454,"y":30.237361053179054,"width":20,"height":20,"activation_condition":"Obstacle","activation":"Activate"},{"x":1256.885635010443,"y":113.90740286811622,"width":20,"height":20,"activation_condition":"Air","activation":"PreventActivate"}],"action":"Bend"}]},{"neurone_web":[{"neurones":[{"x":181.292264927149,"y":8.249453227214698,"width":20,"height":20,"activation_condition":"Obstacle","activation":"Activate"},{"x":54.226248810365036,"y":148.251735812994,"width":20,"height":20,"activation_condition":"Obstacle","activation":"PreventActivate"},{"x":955.0393883001624,"y":12.634680155981833,"width":20,"height":20,"activation_condition":"Obstacle","activation":"Activate"}],"action":"Jump"},{"neurones":[{"x":5.751207760637614,"y":39.575331833601254,"width":20,"height":20,"activation_condition":"Obstacle","activation":"Activate"},{"x":1244.9704800634681,"y":135.63001228385184,"width":20,"height":20,"activation_condition":"Air","activation":"PreventActivate"},{"x":153.4504967280434,"y":320.84979749288703,"width":20,"height":20,"activation_condition":"Obstacle","activation":"PreventActivate"}],"action":"Bend"},{"neurones":[{"x":1052.574409882772,"y":392.1708805064349,"width":20,"height":20,"activation_condition":"Air","activation":"PreventActivate"},{"x":20.24103351214345,"y":264.7929073259521,"width":20,"height":20,"activation_condition":"Obstacle","activation":"PreventActivate"}],"action":"Bend"}]},{"neurone_web":[{"neurones":[{"x":240.79165166024603,"y":36.70772148833112,"width":20,"height":20,"activation_condition":"Obstacle","activation":"Activate"},{"x":56.79411997413821,"y":140.03453548941906,"width":20,"height":20,"activation_condition":"Obstacle","activation":"PreventActivate"},{"x":912.4303055648744,"y":21.01544738183713,"width":20,"height":20,"activation_condition":"Obstacle","activation":"Activate"},{"x":188.46781713208816,"y":693.6579543856922,"width":20,"height":20,"activation_condition":"Obstacle","activation":"PreventActivate"}],"action":"Jump"},{"neurones":[{"x":19.882240218819742,"y":15.857443399527394,"width":20,"height":20,"activation_condition":"Obstacle","activation":"Activate"},{"x":1247.8891849674408,"y":122.56499447147681,"width":20,"height":20,"activation_condition":"Air","activation":"PreventActivate"}],"action":"Bend"}]},{"neurone_web":[{"neurones":[{"x":188.81267153243212,"y":7.0474668217205325,"width":20,"height":20,"activation_condition":"Obstacle","activation":"Activate"},{"x":48.291911815102054,"y":107.6610604667878,"width":20,"height":20,"activation_condition":"Obstacle","activation":"PreventActivate"},{"x":949.9893032878441,"y":24.27667939023815,"width":20,"height":20,"activation_condition":"Obstacle","activation":"Activate"},{"x":991.3442858819297,"y":601.9833297059863,"width":20,"height":20,"activation_condition":"Obstacle","activation":"PreventActivate"}],"action":"Jump"},{"neurones":[{"x":26.964520998059207,"y":48.31299818873398,"width":20,"height":20,"activation_condition":"Obstacle","activation":"Activate"},{"x":1237.4835381660814,"y":109.0783341163272,"width":20,"height":20,"activation_condition":"Air","activation":"PreventActivate"},{"x":1053.8089914806974,"y":287.83703876900046,"width":20,"height":20,"activation_condition":"Obstacle","activation":"Activate"}],"action":"Bend"},{"neurones":[{"x":417.0854418191031,"y":177.4517337497197,"width":20,"height":20,"activation_condition":"Air","activation":"PreventActivate"},{"x":198.33140031876104,"y":75.51297515734989,"width":20,"height":20,"activation_condition":"Air","activation":"Activate"},{"x":569.8815309564058,"y":288.25585525015765,"width":20,"height":20,"activation_condition":"Air","activation":"PreventActivate"}],"action":"Unbend"}]},{"neurone_web":[{"neurones":[{"x":211.6080899073405,"y":36.21647364675298,"width":20,"height":20,"activation_condition":"Obstacle","activation":"Activate"},{"x":93.67178279792132,"y":125.67389846788235,"width":20,"height":20,"activation_condition":"Obstacle","activation":"PreventActivate"},{"x":893.1063815460851,"y":29.582499248834175,"width":20,"height":20,"activation_condition":"Obstacle","activation":"Activate"}],"action":"Jump"},{"neurones":[{"x":19.872902321743048,"y":44.92720030491363,"width":20,"height":20,"activation_condition":"Obstacle","activation":"Activate"},{"x":1167.0113830412795,"y":141.6297768692927,"width":20,"height":20,"activation_condition":"Air","activation":"PreventActivate"},{"x":444.04070382091084,"y":566.4044325657419,"width":20,"height":20,"activation_condition":"Obstacle","activation":"Activate"}],"action":"Bend"}]},{"neurone_web":[{"neurones":[{"x":244.5028401889034,"y":13.820549902033918,"width":20,"height":20,"activation_condition":"Obstacle","activation":"Activate"},{"x":57.17098786253541,"y":134.87391700653075,"width":20,"height":20,"activation_condition":"Obstacle","activation":"PreventActivate"},{"x":950.3403217162709,"y":10.170656173753802,"width":20,"height":20,"activation_condition":"Obstacle","activation":"Activate"}],"action":"Jump"},{"neurones":[{"x":37.03334639405231,"y":79.49724835946911,"width":20,"height":20,"activation_condition":"Obstacle","activation":"Activate"},{"x":1249.2005171600802,"y":117.23884721144529,"width":20,"height":20,"activation_condition":"Air","activation":"PreventActivate"}],"action":"Bend"}]},{"neurone_web":[{"neurones":[{"x":244.0608316927444,"y":13.590799689556722,"width":20,"height":20,"activation_condition":"Obstacle","activation":"Activate"},{"x":75.70425669133365,"y":134.82196881350694,"width":20,"height":20,"activation_condition":"Obstacle","activation":"PreventActivate"},{"x":897.7647645697307,"y":31.937900259532803,"width":20,"height":20,"activation_condition":"Obstacle","activation":"Activate"}],"action":"Jump"},{"neurones":[{"x":95.17003896386235,"y":21.481548638532367,"width":20,"height":20,"activation_condition":"Obstacle","activation":"Activate"},{"x":1238.3699178414493,"y":101.35170185155079,"width":20,"height":20,"activation_condition":"Air","activation":"PreventActivate"},{"x":135.11252371221588,"y":250.20593638991332,"width":20,"height":20,"activation_condition":"Obstacle","activation":"PreventActivate"}],"action":"Bend"}]},{"neurone_web":[{"neurones":[{"x":207.93778002562692,"y":34.29314636656649,"width":20,"height":20,"activation_condition":"Obstacle","activation":"Activate"},{"x":52.090754282133446,"y":146.9071867672935,"width":20,"height":20,"activation_condition":"Obstacle","activation":"PreventActivate"},{"x":908.8535166940621,"y":9.86736615596587,"width":20,"height":20,"activation_condition":"Obstacle","activation":"Activate"}],"action":"Jump"},{"neurones":[{"x":42.86559325670836,"y":68.89431882260253,"width":20,"height":20,"activation_condition":"Obstacle","activation":"Activate"},{"x":1217.8512678489574,"y":98.88643416764344,"width":20,"height":20,"activation_condition":"Air","activation":"PreventActivate"},{"x":218.1357133587441,"y":427.75149498090644,"width":20,"height":20,"activation_condition":"Obstacle","activation":"PreventActivate"}],"action":"Bend"},{"neurones":[{"x":575.1927918224744,"y":308.65009063586086,"width":20,"height":20,"activation_condition":"Air","activation":"Activate"},{"x":85.54507680438972,"y":325.7110313470781,"width":20,"height":20,"activation_condition":"Obstacle","activation":"PreventActivate"},{"x":427.76063317354493,"y":223.66085467966863,"width":20,"height":20,"activation_condition":"Air","activation":"Activate"},{"x":342.87283374160984,"y":521.6852925167153,"width":20,"height":20,"activation_condition":"Air","activation":"PreventActivate"},{"x":56.10816742330733,"y":260.8711479937801,"width":20,"height":20,"activation_condition":"Air","activation":"Activate"}],"action":"Jump"}]},{"neurone_web":[{"neurones":[{"x":234.81867571436777,"y":39.12041385053147,"width":20,"height":20,"activation_condition":"Obstacle","activation":"Activate"},{"x":79.30832944307622,"y":129.13490151911117,"width":20,"height":20,"activation_condition":"Obstacle","activation":"PreventActivate"},{"x":896.7195851472405,"y":25.42925515656889,"width":20,"height":20,"activation_condition":"Obstacle","activation":"Activate"},{"x":162.73636064053304,"y":537.2826951561825,"width":20,"height":20,"activation_condition":"Obstacle","activation":"Activate"}],"action":"Jump"},{"neurones":[{"x":5.886522882145458,"y":86.16757557528678,"width":20,"height":20,"activation_condition":"Obstacle","activation":"Activate"},{"x":1255.0607304784962,"y":118.37072417964895,"width":20,"height":20,"activation_condition":"Air","activation":"PreventActivate"},{"x":526.5283194517465,"y":692.37005130425,"width":20,"height":20,"activation_condition":"Obstacle","activation":"Activate"},{"x":7.770544323693582,"y":533.8911263506898,"width":20,"height":20,"activation_condition":"Obstacle","activation":"Activate"}],"action":"Bend"}]},{"neurone_web":[{"neurones":[{"x":195.4301822733615,"y":14.647830731741657,"width":20,"height":20,"activation_condition":"Obstacle","activation":"Activate"},{"x":48.955868290658024,"y":129.49872271010628,"width":20,"height":20,"activation_condition":"Obstacle","activation":"PreventActivate"},{"x":904.165952559869,"y":39.87240185016664,"width":20,"height":20,"activation_condition":"Obstacle","activation":"Activate"},{"x":536.8121065667362,"y":501.5665285104927,"width":20,"height":20,"activation_condition":"Obstacle","activation":"Activate"},{"x":785.4758075433444,"y":477.4342668121438,"width":20,"height":20,"activation_condition":"Obstacle","activation":"PreventActivate"}],"action":"Jump"},{"neurones":[{"x":21.617981153251716,"y":55.986377448366255,"width":20,"height":20,"activation_condition":"Obstacle","activation":"Activate"},{"x":1181.1987418544923,"y":100.95331152343081,"width":20,"height":20,"activation_condition":"Air","activation":"PreventActivate"}],"action":"Bend"},{"neurones":[{"x":769.9418835495121,"y":610.9871389037469,"width":20,"height":20,"activation_condition":"Obstacle","activation":"PreventActivate"},{"x":209.50982368682986,"y":97.23190239575379,"width":20,"height":20,"activation_condition":"Air","activation":"PreventActivate"},{"x":287.8894870826688,"y":258.66232422739535,"width":20,"height":20,"activation_condition":"Obstacle","activation":"PreventActivate"},{"x":656.9095264066157,"y":474.0344648077044,"width":20,"height":20,"activation_condition":"Obstacle","activation":"PreventActivate"}],"action":"Bend"},{"neurones":[{"x":860.7038051667695,"y":609.4702657478994,"width":20,"height":20,"activation_condition":"Air","activation":"PreventActivate"},{"x":5.040450533517178,"y":137.66589021764503,"width":20,"height":20,"activation_condition":"Obstacle","activation":"Activate"}],"action":"Unbend"}]},{"neurone_web":[{"neurones":[{"x":190.9296097708312,"y":29.2510517975435,"width":20,"height":20,"activation_condition":"Obstacle","activation":"Activate"},{"x":51.42388325448063,"y":97.99388326592164,"width":20,"height":20,"activation_condition":"Obstacle","activation":"PreventActivate"},{"x":893.9056585520896,"y":31.9745112395471,"width":20,"height":20,"activation_condition":"Obstacle","activation":"Activate"}],"action":"Jump"},{"neurones":[{"x":3.2579030318021442,"y":45.87551743889438,"width":20,"height":20,"activation_condition":"Obstacle","activation":"Activate"},{"x":1193.7635026815321,"y":147.71227015584884,"width":20,"height":20,"activation_condition":"Air","activation":"PreventActivate"}],"action":"Bend"}]},{"neurone_web":[{"neurones":[{"x":234.7725366872403,"y":29.20134782882199,"width":20,"height":20,"activation_condition":"Obstacle","activation":"Activate"},{"x":127.42830362195812,"y":141.6526904382613,"width":20,"height":20,"activation_condition":"Obstacle","activation":"PreventActivate"},{"x":896.0706034593842,"y":37.103124085005696,"width":20,"height":20,"activation_condition":"Obstacle","activation":"Activate"},{"x":853.0850790948015,"y":651.6678735156711,"width":20,"height":20,"activation_condition":"Obstacle","activation":"PreventActivate"}],"action":"Jump"},{"neurones":[{"x":87.01358486203213,"y":49.22821102154044,"width":20,"height":20,"activation_condition":"Obstacle","activation":"Activate"},{"x":1234.8919635612533,"y":145.58074335884413,"width":20,"height":20,"activation_condition":"Air","activation":"PreventActivate"}],"action":"Bend"}]},{"neurone_web":[{"neurones":[{"x":205.2430803514071,"y":17.040190935968074,"width":20,"height":20,"activation_condition":"Obstacle","activation":"Activate"},{"x":65.86735059739465,"y":117.50985049921262,"width":20,"height":20,"activation_condition":"Obstacle","activation":"PreventActivate"},{"x":902.5656866037049,"y":26.683558835026677,"width":20,"height":20,"activation_condition":"Obstacle","activation":"Activate"},{"x":252.16040142525665,"y":538.6608923120789,"width":20,"height":20,"activation_condition":"Obstacle","activation":"PreventActivate"}],"action":"Jump"},{"neurones":[{"x":77.02037632051517,"y":43.40783165852511,"width":20,"height":20,"activation_condition":"Obstacle","activation":"Activate"},{"x":1231.2169154133912,"y":144.6834572761579,"width":20,"height":20,"activation_condition":"Air","activation":"PreventActivate"}],"action":"Bend"},{"neurones":[{"x":393.93275570789615,"y":150.83483940702612,"width":20,"height":20,"activation_condition":"Air","activation":"PreventActivate"},{"x":142.08334996973886,"y":33.20268540999089,"width":20,"height":20,"activation_condition":"Air","activation":"Activate"},{"x":826.8205592052508,"y":583.3809408001257,"width":20,"height":20,"activation_condition":"Air","activation":"PreventActivate"},{"x":805.7408066756573,"y":324.71549837726985,"width":20,"height":20,"activation_condition":"Obstacle","activation":"PreventActivate"}],"action":"Unbend"}]},{"neurone_web":[{"neurones":[{"x":204.00321327092104,"y":13.210261554321448,"width":20,"height":20,"activation_condition":"Obstacle","activation":"Activate"},{"x":91.34769228216626,"y":107.77960781064445,"width":20,"height":20,"activation_condition":"Obstacle","activation":"PreventActivate"},{"x":898.9684902459147,"y":24.168799838239693,"width":20,"height":20,"activation_condition":"Obstacle","activation":"Activate"},{"x":203.32518893064886,"y":526.7353940054724,"width":20,"height":20,"activation_condition":"Obstacle","activation":"PreventActivate"}],"action":"Jump"},{"neurones":[{"x":38.47626257723333,"y":14.368821803164106,"width":20,"height":20,"activation_condition":"Obstacle","activation":"Activate"},{"x":1245.4577601169465,"y":132.2588785872833,"width":20,"height":20,"activation_condition":"Air","activation":"PreventActivate"}],"action":"Bend"},{"neurones":[{"x":438.1826776789098,"y":153.6710548499568,"width":20,"height":20,"activation_condition":"Air","activation":"PreventActivate"},{"x":136.39183803065376,"y":29.778816293064477,"width":20,"height":20,"activation_condition":"Air","activation":"Activate"},{"x":866.7452049770479,"y":612.0240178664499,"width":20,"height":20,"activation_condition":"Air","activation":"PreventActivate"},{"x":931.142203145376,"y":121.34205849714984,"width":20,"height":20,"activation_condition":"Air","activation":"Activate"}],"action":"Unbend"}]},{"neurone_web":[{"neurones":[{"x":240.379532798844,"y":26.120176672752425,"width":20,"height":20,"activation_condition":"Obstacle","activation":"Activate"},{"x":115.24129770126997,"y":99.55742605499259,"width":20,"height":20,"activation_condition":"Obstacle","activation":"PreventActivate"},{"x":896.6485531022033,"y":22.587528877756032,"width":20,"height":20,"activation_condition":"Obstacle","activation":"Activate"}],"action":"Jump"},{"neurones":[{"x":67.95122664033725,"y":64.21932910879687,"width":20,"height":20,"activation_condition":"Obstacle","activation":"Activate"},{"x":1190.2803608085235,"y":133.570239764068,"width":20,"height":20,"activation_condition":"Air","activation":"PreventActivate"},{"x":23.47468968089773,"y":156.32559861248797,"width":20,"height":20,"activation_condition":"Obstacle","activation":"PreventActivate"},{"x":1001.2854378694248,"y":650.9131326221355,"width":20,"height":20,"activation_condition":"Obstacle","activation":"Activate"}],"action":"Bend"}]}],"rng":{"state":89781366180193155087320339431974792391,"increment":1},"score":9}