{"brains":[{"neurone_web":[{"neurones":[{"x":219.46202076016144,"y":29.583704720451543,"width":20,"height":20,"activation_condition":"Obstacle","activation":"Activate"},{"x":50.89881090667308,"y":145.60029833994435,"width":20,"height":20,"activation_condition":"Obstacle","activation":"PreventActivate"},{"x":930.1746092163958,"y":31.63918237505106,"width":20,"height":20,"activation_condition":"Obstacle","activation":"Activate"}],"action":"Jump"},{"neurones":[{"x":83.94332986195519,"y":18.508771597452917,"width":20,"height":20,"activation_condition":"Obstacle","activation":"Activate"},{"x":1216.2275701532528,"y":130.40671157052597,"width":20,"height":20,"activation_condition":"Air","activation":"PreventActivate"}],"action":"Bend"}]},{"neurone_web":[{"neurones":[{"x":220.04873591697148,"y":27.035394398609867,"width":20,"height":20,"activation_condition":"Obstacle","activation":"Activate"},{"x":91.89171669139989,"y":149.01674080211603,"width":20,"height":20,"activation_condition":"Obstacle","activation":"PreventActivate"},{"x":902.6831829357935,"y":16.040282331757695,"width":20,"height":20,"activation_condition":"Obstacle","activation":"Activate"}],"action":"Jump"},{"neurones":[{"x":22.207736675857,"y":16.941153436306287,"width":20,"height":20,"activation_condition":"Obstacle","activation":"Activate"},{"x":1227.4988296549518,"y":96.1943385605034,"width":20,"height":20,"activation_condition":"Air","activation":"PreventActivate"}],"action":"Bend"}]},{"neurone_web":[{"neurones":[{"x":192.50197614156468,"y":21.792613475604583,"width":20,"height":20,"activation_condition":"Obstacle","activation":"Activate"},{"x":53.33509900224418,"y":91.97560621319865,"width":20,"height":20,"activation_condition":"Obstacle","activation":"PreventActivate"},{"x":923.3382604673509,"y":22.892582104015062,"width":20,"height":20,"activation_condition":"Obstacle","activation":"Activate"}],"action":"Jump"},{"neurones":[{"x":1212.871483292038,"y":107.59996340174095,"width":20,"height":20,"activation_condition":"Air","activation":"PreventActivate"},{"x":49.69799817734723,"y":99.32539486549216,"width":20,"height":20,"activation_condition":"Obstacle","activation":"Activate"}],"action":"Bend"},{"neurones":[{"x":176.91320733304158,"y":358.08060415699225,"width":20,"height":20,"activation_condition":"Obstacle","activation":"Activate"}],"action":"Jump"}]},{"neurone_web":[{"neurones":[{"x":212.37981650747372,"y":33.60658080465102,"width":20,"height":20,"activation_condition":"Obstacle","activation":"Activate"},{"x":53.681274283311794,"y":108.10675639746226,"width":20,"height":20,"activation_condition":"Obstacle","activation":"PreventActivate"},{"x":923.9958118664132,"y":29.33815326964312,"width":20,"height":20,"activation_condition":"Obstacle","activation":"Activate"},{"x":808.1294312543201,"y":351.874877702469,"width":20,"height":20,"activation_condition":"Obstacle","activation":"PreventActivate"}],"action":"Jump"},{"neurones":[{"x":15.932655999979449,"y":69.50644003965279,"width":20,"height":20,"activation_condition":"Obstacle","activation":"Activate"},{"x":1225.8602614584229,"y":115.83961153387257,"width":20,"height":20,"activation_condition":"Air","activation":"PreventActivate"}],"action":"Bend"},{"neurones":[{"x":569.935050101664,"y":266.1495295047007,"width":20,"height":20,"activation_condition":"Air","activation":"Activate"},{"x":1225.1613591042033,"y":192.47108294846694,"width":20,"height":20,"activation_condition":"Air","activation":"Activate"},{"x":1021.77688540653,"y":443.2977252410224,"width":20,"height":20,"activation_condition":"Air","activation":"PreventActivate"}],"action":"Jump"}]},{"neurone_web":[{"neurones":[{"x":203.26094566622055,"y":8.102658065391495,"width":20,"height":20,"activation_condition":"Obstacle","activation":"Activate"},{"x":78.54843948539389,"y":145.43195468980838,"width":20,"height":20,"activation_condition":"Obstacle","activation":"PreventActivate"},{"x":901.1321816216143,"y":26.532295639056258,"width":20,"height":20,"activation_condition":"Obstacle","activation":"Activate"}],"action":"Jump"},{"neurones":[{"x":1233.7909978255946,"y":104.80852615472793,"width":20,"height":20,"activation_condition":"Air","activation":"PreventActivate"},{"x":18.169845105520672,"y":48.80648496896879,"width":20,"height":20,"activation_condition":"Obstacle","activation":"Activate"}],"action":"Bend"},{"neurones":[{"x":569.6358007870052,"y":155.85803848996585,"width":20,"height":20,"activation_condition":"Obstacle","activation":"PreventActivate"},{"x":120.96287950907131,"y":247.97396061429376,"width":20,"height":20,"activation_condition":"Air","activation":"PreventActivate"},{"x":355.0462019126991,"y":484.6367836253544,"width":20,"height":20,"activation_condition":"Obstacle","activation":"Activate"},{"x":404.4218907943481,"y":502.60922575220457,"width":20,"height":20,"activation_condition":"Air","activation":"Activate"},{"x":921.6911493855173,"y":470.8486176116958,"width":20,"height":20,"activation_condition":"Obstacle","activation":"Activate"},{"x":699.6429818650154,"y":148.88629489939498,"width":20,"height":20,"activation_condition":"Air","activation":"PreventActivate"}],"action":"Jump"}]},{"neurone_web":[{"neurones":[{"x":206.66556302637213,"y":29.06836311658163,"width":20,"height":20,"activation_condition":"Obstacle","activation":"Activate"},{"x":69.20537280066593,"y":149.1323872583074,"width":20,"height":20,"activation_condition":"Obstacle","activation":"PreventActivate"},{"x":900.1654337270527,"y":37.11086397259084,"width":20,"height":20,"activation_condition":"Obstacle","activation":"Activate"}],"action":"Jump"},{"neurones":[{"x":79.25074065760491,"y":75.0551681149731,"width":20,"height":20,"activation_condition":"Obstacle","activation":"Activate"},{"x":1209.6140857243545,"y":126.36353509395069,"width":20,"height":20,"activation_condition":"Air","activation":"PreventActivate"},{"x":435.6843625978972,"y":603.4898825634347,"width":20,"height":20,"activation_condition":"Obstacle","activation":"PreventActivate"}],"action":"Bend"},{"neurones":[{"x":826.3207362347266,"y":176.93390629223035,"width":20,"height":20,"activation_condition":"Air","activation":"Activate"},{"x":1063.4821007444332,"y":611.0390135505897,"width":20,"height":20,"activation_condition":"Air","activation":"PreventActivate"}],"action":"Unbend"}]},{"neurone_web":[{"neurones":[{"x":170.8288959149277,"y":26.392274415319694,"width":20,"height":20,"activation_condition":"Obstacle","activation":"Activate"},{"x":55.17513626756184,"y":95.94218845129572,"width":20,"height":20,"activation_condition":"Obstacle","activation":"PreventActivate"},{"x":902.4713194081879,"y":28.52616762809316,"width":20,"height":20,"activation_condition":"Obstacle","activation":"Activate"},{"x":197.48877071339038,"y":485.6201562198479,"width":20,"height":20,"activation_condition":"Obstacle","activation":"PreventActivate"}],"action":"Jump"},{"neurones":[{"x":8.78394923992829,"y":8.053823867254136,"width":20,"height":20,"activation_condition":"Obstacle","activation":"Activate"},{"x":1245.984046329509,"y":95.46815286068595,"width":20,"height":20,"activation_condition":"Air","activation":"PreventActivate"},{"x":357.63951011876793,"y":568.7312510230715,"width":20,"height":20,"activation_condition":"Obstacle","activation":"PreventActivate"}],"action":"Bend"},{"neurones":[{"x":1228.9624139487962,"y":133.1201575630692,"width":20,"height":20,"activation_condition":"Obstacle","activation":"PreventActivate"},{"x":633.9065073437172,"y":435.6503096150794,"width":20,"height":20,"activation_condition":"Obstacle","activation":"PreventActivate"},{"x":1160.036783152043,"y":558.376825444943,"width":20,"height":20,"activation_condition":"Air","activation":"PreventActivate"}],"action":"Unbend"}]},{"neurone_web":[{"neurones":[{"x":237.568286916785,"y":14.016125486954046,"width":20,"height":20,"activation_condition":"Obstacle","activation":"Activate"},{"x":91.43433486194033,"y":108.85684719562093,"width":20,"height":20,"activation_condition":"Obstacle","activation":"PreventActivate"},{"x":902.4553712199058,"y":9.666891778719314,"width":20,"height":20,"activation_condition":"Obstacle","activation":"Activate"}],"action":"Jump"},{"neurones":[{"x":15.677397374894923,"y":45.06988583219114,"width":20,"height":20,"activation_condition":"Obstacle","activation":"Activate"},{"x":1177.2351649812083,"y":128.71413842382628,"width":20,"height":20,"activation_condition":"Air","activation":"PreventActivate"},{"x":895.5499206496186,"y":294.8958143828195,"width":20,"height":20,"activation_condition":"Obstacle","activation":"PreventActivate"}],"action":"Bend"},{"neurones":[{"x":790.8064967993325,"y":456.2344435195315,"width":20,"height":20,"activation_condition":"Obstacle","activation":"PreventActivate"},{"x":79.12301683987405,"y":442.39066075585833,"width":20,"height":20,"activation_condition":"Air","activation":"PreventActivate"}],"action":"Unbend"}]},{"neurone_web":[{"neurones":[{"x":170.97112359245887,"y":38.403305904345686,"width":20,"height":20,"activation_condition":"Obstacle","activation":"Activate"},{"x":47.01732828803268,"y":132.47871780834942,"width":20,"height":20,"activation_condition":"Obstacle","activation":"PreventActivate"},{"x":922.3298908993609,"y":28.46904306252375,"width":20,"height":20,"activation_condition":"Obstacle","activation":"Activate"},{"x":408.34613662659103,"y":253.46228991142766,"width":20,"height":20,"activation_condition":"Obstacle","activation":"PreventActivate"}],"action":"Jump"},{"neurones":[{"x":67.50924126239319,"y":52.019154628304946,"width":20,"height":20,"activation_condition":"Obstacle","activation":"Activate"},{"x":1201.3697314497115,"y":119.18841030551208,"width":20,"height":20,"activation_condition":"Air","activation":"PreventActivate"},{"x":1105.6132999945646,"y":356.8721067275343,"width":20,"height":20,"activation_condition":"Obstacle","activation":"Activate"}],"action":"Bend"}]},{"neurone_web":[{"neurones":[{"x":259.7122560286647,"y":24.44163924561937,"width":20,"height":20,"activation_condition":"Obstacle","activation":"Activate"},{"x":97.94576349598279,"y":130.73203874172012,"width":20,"height":20,"activation_condition":"Obstacle","activation":"PreventActivate"},{"x":899.1559544701513,"y":21.217290302311994,"width":20,"height":20,"activation_condition":"Obstacle","activation":"Activate"}],"action":"Jump"},{"neurones":[{"x":104.1091585503245,"y":31.16387741496149,"width":20,"height":20,"activation_condition":"Obstacle","activation":"Activate"},{"x":1232.2147047855108,"y":103.24342100933904,"width":20,"height":20,"activation_condition":"Air","activation":"PreventActivate"}],"action":"Bend"}]},{"neurone_web":[{"neurones":[{"x":191.07555326497308,"y":18.53944776868268,"width":20,"height":20,"activation_condition":"Obstacle","activation":"Activate"},{"x":53.63936719351954,"y":107.58502078594499,"width":20,"height":20,"activation_condition":"Obstacle","activation":"PreventActivate"},{"x":917.4951666801462,"y":9.109051248957776,"width":20,"height":20,"activation_condition":"Obstacle","activation":"Activate"}],"action":"Jump"},{"neurones":[{"x":6.283729513968651,"y":10.842078573422608,"width":20,"height":20,"activation_condition":"Obstacle","activation":"Activate"},{"x":1133.656425634939,"y":142.99114154275074,"width":20,"height":20,"activation_condition":"Air","activation":"PreventActivate"},{"x":914.4954610135941,"y":295.844077610572,"width":20,"height":20,"activation_condition":"Obstacle","activation":"PreventActivate"}],"action":"Bend"},{"neurones":[{"x":864.4719262341779,"y":479.1577167484667,"width":20,"height":20,"activation_condition":"Obstacle","activation":"PreventActivate"},{"x":852.7173986784934,"y":144.56140414961337,"width":20,"height":20,"activation_condition":"Air","activation":"Activate"},{"x":67.20771560406031,"y":455.91405693946115,"width":20,"height":20,"activation_condition":"Air","activation":"PreventActivate"},{"x":653.2955688638181,"y":498.71322554358045,"width":20,"height":20,"activation_condition":"Air","activation":"Activate"}],"action":"Unbend"}]},{"neurone_web":[{"neurones":[{"x":208.11139466338298,"y":38.87026735336602,"width":20,"height":20,"activation_condition":"Obstacle","activation":"Activate"},{"x":49.63953697587662,"y":129.1923205793678,"width":20,"height":20,"activation_condition":"Obstacle","activation":"PreventActivate"},{"x":941.5725011626671,"y":36.67985757858926,"width":20,"height":20,"activation_condition":"Obstacle","activation":"Activate"}],"action":"Jump"},{"neurones":[{"x":79.32437046680525,"y":39.78546965835508,"width":20,"height":20,"activation_condition":"Obstacle","activation":"Activate"},{"x":1222.4567104838873,"y":119.14884318840575,"width":20,"height":20,"activation_condition":"Air","activation":"PreventActivate"}],"action":"Bend"},{"neurones":[{"x":801.3953638282686,"y":558.2337708328478,"width":20,"height":20,"activation_condition":"Air","activation":"PreventActivate"},{"x":1034.1187210082194,"y":12.509086378617134,"width":20,"height":20,"activation_condition":"Obstacle","activation":"PreventActivate"}],"action":"Jump"}]},{"neurone_web":[{"neurones":[{"x":212.45614972522446,"y":36.06701928166048,"width":20,"height":20,"activation_condition":"Obstacle","activation":"Activate"},{"x":56.98444231277924,"y":91.39190939777018,"width":20,"height":20,"activation_condition":"Obstacle","activation":"PreventActivate"},{"x":951.4319473483479,"y":27.765922864323734,"width":20,"height":20,"activation_condition":"Obstacle","activation":"Activate"},{"x":191.24177955892708,"y":441.1803695799654,"width":20,"height":20,"activation_condition":"Obstacle","activation":"Activate"}],"action":"Jump"},{"neurones":[{"x":13.133312467388036,"y":50.352610207116726,"width":20,"height":20,"activation_condition":"Obstacle","activation":"Activate"},{"x":1169.5239887155142,"y":119.61731275412947,"width":20,"height":20,"activation_condition":"Air","activation":"PreventActivate"},{"x":912.3677180183117,"y":306.2540767954388,"width":20,"height":20,"activation_condition":"Obstacle","activation":"PreventActivate"}],"action":"Bend"},{"neurones":[{"x":481.1995956709363,"y":305.4792243863389,"width":20,"height":20,"activation_condition":"Air","activation":"Activate"},{"x":397.3597469859567,"y":497.31501500374225,"width":20,"height":20,"activation_condition":"Air","activation":"PreventActivate"},{"x":379.97951880024516,"y":695.7190158122344,"width":20,"height":20,"activation_condition":"Obstacle","activation":"Activate"},{"x":556.4531216788101,"y":409.58255678737305,"width":20,"height":20,"activation_condition":"Obstacle","activation":"Activate"}],"action":"Unbend"},{"neurones":[{"x":820.0927999734471,"y":507.18778889813836,"width":20,"height":20,"activation_condition":"Obstacle","activation":"PreventActivate"},{"x":878.0044808162118,"y":193.92642515658113,"width":20,"height":20,"activation_condition":"Air","activation":"Activate"},{"x":19.96660785628537,"y":485.06663615183794,"width":20,"height":20,"activation_condition":"Air","activation":"PreventActivate"},{"x":376.7165585927337,"y":81.54817232063016,"width":20,"height":20,"activation_condition":"Air","activation":"Activate"},{"x":695.8152303804878,"y":538.4307328207314,"width":20,"height":20,"activation_condition":"Air","activation":"Activate"}],"action":"Unbend"}]},{"neurone_web":[{"neurones":[{"x":255.47532106412322,"y":38.83692040917485,"width":20,"height":20,"activation_condition":"Obstacle","activation":"Activate"},{"x":88.29946153093442,"y":100.47290419706711,"width":20,"height":20,"activation_condition":"Obstacle","activation":"PreventActivate"},{"x":895.3668113575505,"y":24.00375994295997,"width":20,"height":20,"activation_condition":"Obstacle","activation":"Activate"},{"x":974.5130486863499,"y":400.8634239882137,"width":20,"height":20,"activation_condition":"Obstacle","activation":"Activate"}],"action":"Jump"},{"neurones":[{"x":2.9032474363915717,"y":27.430726317360516,"width":20,"height":20,"activation_condition":"Obstacle","activation":"Activate"},{"x":1217.4060978408638,"y":107.67786029542745,"width":20,"height":20,"activation_condition":"Air","activation":"PreventActivate"}],"action":"Bend"}]},{"neurone_web":[{"neurones":[{"x":210.2088746678049,"y":17.7247705478987,"width":20,"height":20,"activation_condition":"Obstacle","activation":"Activate"},{"x":59.60571891744424,"y":117.81922002756126,"width":20,"height":20,"activation_condition":"Obstacle","activation":"PreventActivate"},{"x":925.6071504458898,"y":10.251635457502337,"width":20,"height":20,"activation_condition":"Obstacle","activation":"Activate"},{"x":180.14814080512653,"y":493.1281238311207,"width":20,"height":20,"activation_condition":"Obstacle","activation":"Activate"}],"action":"Jump"},{"neurones":[{"x":25.600802056318233,"y":71.60949961177809,"width":20,"height":20,"activation_condition":"Obstacle","activation":"Activate"},{"x":1176.8570200800789,"y":111.10893023170907,"width":20,"height":20,"activation_condition":"Air","activation":"PreventActivate"}],"action":"Bend"},{"neurones":[{"x":440.9654415089296,"y":225.78123289625006,"width":20,"height":20,"activation_condition":"Air","activation":"Activate"},{"x":268.2168544198534,"y":480.62514227639895,"width":20,"height":20,"activation_condition":"Obstacle","activation":"Activate"},{"x":344.4420085628756,"y":533.2404126264172,"width":20,"height":20,"activation_condition":"Air","activation":"PreventActivate"},{"x":394.3809895174576,"y":605.9480667205678,"width":20,"height":20,"activation_condition":"Obstacle","activation":"Activate"}],"action":"Unbend"},{"neurones":[{"x":809.2868706263931,"y":116.80332567703016,"width":20,"height":20,"activation_condition":"Air","activation":"Activate"},{"x":748.9601389325544,"y":693.8432247061808,"width":20,"height":20,"activation_condition":"Obstacle","activation":"PreventActivate"},{"x":129.50750137377005,"y":514.8143621378692,"width":20,"height":20,"activation_condition":"Air","activation":"PreventActivate"}],"action":"Unbend"}]},{"neurone_web":[{"neurones":[{"x":201.15026477272923,"y":9.49855369378853,"width":20,"height":20,"activation_condition":"Obstacle","activation":"Activate"},{"x":59.50454181470706,"y":111.82101020544783,"width":20,"height":20,"activation_condition":"Obstacle","activation":"PreventActivate"},{"x":898.996194778783,"y":16.20354643889486,"width":20,"height":20,"activation_condition":"Obstacle","activation":"Activate"},{"x":674.8739438348105,"y":658.8556483608157,"width":20,"height":20,"activation_condition":"Obstacle","activation":"Activate"},{"x":553.141094284833,"y":101.74085170249745,"width":20,"height":20,"activation_condition":"Obstacle","activation":"PreventActivate"}],"action":"Jump"},{"neurones":[{"x":0.9179311378056396,"y":78.36278390020603,"width":20,"height":20,"activation_condition":"Obstacle","activation":"Activate"},{"x":1155.80443920602,"y":113.46303135687205,"width":20,"height":20,"activation_condition":"Air","activation":"PreventActivate"}],"action":"Bend"},{"neurones":[{"x":312.88818875625964,"y":591.0038960580445,"width":20,"height":20,"activation_condition":"Obstacle","activation":"Activate"},{"x":989.9199327320677,"y":273.520601787873,"width":20,"height":20,"activation_condition":"Obstacle","activation":"Activate"},{"x":752.2213186642128,"y":170.01926730403704,"width":20,"height":20,"activation_condition":"Air","activation":"PreventActivate"},{"x":1141.2729038520417,"y":314.09997875018587,"width":20,"height":20,"activation_condition":"Air","activation":"PreventActivate"}],"action":"Bend"}]},{"neurone_web":[{"neurones":[{"x":58.47265811987467,"y":135.8166346326458,"width":20,"height":20,"activation_condition":"Obstacle","activation":"PreventActivate"},{"x":944.2974225919863,"y":36.435878706351716,"width":20,"height":20,"activation_condition":"Obstacle","activation":"Activate"},{"x":209.86758150213058,"y":29.94384594570821,"width":20,"height":20,"activation_condition":"Obstacle","activation":"Activate"},{"x":119.67299300567309,"y":504.2042708955286,"width":20,"height":20,"activation_condition":"Obstacle","activation":"Activate"}],"action":"Jump"},{"neurones":[{"x":36.20069202248185,"y":60.814508538156836,"width":20,"height":20,"activation_condition":"Obstacle","activation":"Activate"},{"x":1233.2109143532462,"y":141.081745645955,"width":20,"height":20,"activation_condition":"Air","activation":"PreventActivate"}],"action":"Bend"},{"neurones":[{"x":117.0514980874932,"y":328.41531257460747,"width":20,"height":20,"activation_condition":"Air","activation":"Activate"},{"x":1111.7704423024754,"y":634.38801162577,"width":20,"height":20,"activation_condition":"Air","activation":"PreventActivate"}],"action":"Unbend"}]},{"neurone_web":[{"neurones":[{"x":224.07280140371648,"y":33.26882969895386,"width":20,"height":20,"activation_condition":"Obstacle","activation":"Activate"},{"x":104.79649921625652,"y":118.96625959849683,"width":20,"height":20,"activation_condition":"Obstacle","activation":"PreventActivate"},{"x":904.1112312578258,"y":19.287337084534624,"width":20,"height":20,"activation_condition":"Obstacle","activation":"Activate"}],"action":"Jump"},{"neurones":[{"x":1236.0531577679885,"y":117.43182703339284,"width":20,"height":20,"activation_condition":"Air","activation":"PreventActivate"},{"x":26.856698492425146,"y":47.62511329976941,"width":20,"height":20,"activation_condition":"Obstacle","activation":"Activate"}],"action":"Bend"}]},{"neurone_web":[{"neurones":[{"x":214.15452561735717,"y":9.080413014015566,"width":20,"height":20,"activation_condition":"Obstacle","activation":"Activate"},{"x":70.23418752723272,"y":143.53208047840724,"width":20,"height":20,"activation_condition":"Obstacle","activation":"PreventActivate"},{"x":894.1286110545237,"y":27.215317479533237,"width":20,"height":20,"activation_condition":"Obstacle","activation":"Activate"},{"x":679.6602009425955,"y":664.0139921331202,"width":20,"height":20,"activation_condition":"Obstacle","activation":"Activate"}],"action":"Jump"},{"neurones":[{"x":22.97598301210909,"y":71.20139269353393,"width":20,"height":20,"activation_condition":"Obstacle","activation":"Activate"},{"x":1171.8356887994466,"y":113.43535178175094,"width":20,"height":20,"activation_condition":"Air","activation":"PreventActivate"}],"action":"Bend"}]},{"neurone_web":[{"neurones":[{"x":193.44458246255164,"y":37.8162113220679,"width":20,"height":20,"activation_condition":"Obstacle","activation":"Activate"},{"x":54.83816950376666,"y":122.4471650061863,"width":20,"height":20,"activation_condition":"Obstacle","activation":"PreventActivate"},{"x":945.0478176626701,"y":9.7044468555801,"width":20,"height":20,"activation_condition":"Obstacle","activation":"Activate"},{"x":218.9049875989415,"y":459.4100051261537,"width":20,"height":20,"activation_condition":"Obstacle","activation":"Activate"}],"action":"Jump"},{"neurones":[{"x":39.918175841983306,"y":67.83600024250657,"width":20,"height":20,"activation_condition":"Obstacle","activation":"Activate"},{"x":1179.772581166471,"y":139.01973449844184,"width":20,"height":20,"activation_condition":"Air","activation":"PreventActivate"}],"action":"Bend"},{"neurones":[{"x":264.7642609736073,"y":497.34415738514116,"width":20,"height":20,"activation_condition":"Obstacle","activation":"Activate"},{"x":352.9255496849821,"y":494.21992874782813,"width":20,"height":20,"activation_condition":"Air","activation":"PreventActivate"},{"x":351.9092468330286,"y":616.3616750071789,"width":20,"height":20,"activation_condition":"Obstacle","activation":"Activate"}],"action":"Unbend"},{"neurones":[{"x":1129.8771437667313,"y":324.6151138426719,"width":20,"height":20,"activation_condition":"Obstacle","activation":"Activate"},{"x":863.6748795111063,"y":491.47792519599284,"width":20,"height":20,"activation_condition":"Obstacle","activation":"PreventActivate"},{"x":801.651421296772,"y":691.3080556274239,"width":20,"height":20,"activation_condition":"Air","activation":"PreventActivate"}],"action":"Bend"}]},{"neurone_web":[{"neurones":[{"x":191.1000612267467,"y":39.28076335719773,"width":20,"height":20,"activation_condition":"Obstacle","activation":"Activate"},{"x":52.164821655360626,"y":103.16637420722495,"width":20,"height":20,"activation_condition":"Obstacle","activation":"PreventActivate"},{"x":896.3047266663832,"y":37.86410450661428,"width":20,"height":20,"activation_condition":"Obstacle","activation":"Activate"},{"x":851.4524548109639,"y":400.1683537575074,"width":20,"height":20,"activation_condition":"Obstacle","activation":"PreventActivate"}],"action":"Jump"},{"neurones":[{"x":36.26181084681967,"y":71.37087770506754,"width":20,"height":20,"activation_condition":"Obstacle","activation":"Activate"},{"x":1192.0772189210988,"y":120.00717422663132,"width":20,"height":20,"activation_condition":"Air","activation":"PreventActivate"}],"action":"Bend"}]},{"neurone_web":[{"neurones":[{"x":212.83300885535897,"y":22.767033300207956,"width":20,"height":20,"activation_condition":"Obstacle","activation":"Activate"},{"x":92.37202601880719,"y":112.37645756873295,"width":20,"height":20,"activation_condition":"Obstacle","activation":"PreventActivate"},{"x":904.4446798341257,"y":8.285899872146071,"width":20,"height":20,"activation_condition":"Obstacle","activation":"Activate"},{"x":1179.7751256226413,"y":541.166601043668,"width":20,"height":20,"activation_condition":"Obstacle","activation":"PreventActivate"}],"action":"Jump"},{"neurones":[{"x":1210.130858804522,"y":124.28369092534773,"width":20,"height":20,"activation_condition":"Air","activation":"PreventActivate"},{"x":16.43307625013901,"y":74.2233569216984,"width":20,"height":20,"activation_condition":"Obstacle","activation":"Activate"},{"x":165.22184032415345,"y":531.3869122314306,"width":20,"height":20,"activation_condition":"Obstacle","activation":"Activate"}],"action":"Bend"},{"neurones":[{"x":636.6378024425716,"y":104.06894374672143,"width":20,"height":20,"activation_condition":"Obstacle","activation":"Activate"},{"x":821.1131940306219,"y":210.65692067449032,"width":20,"height":20,"activation_condition":"Air","activation":"PreventActivate"}],"action":"Jump"}]},{"neurone_web":[{"neurones":[{"x":225.4479487626379,"y":18.46051503758662,"width":20,"height":20,"activation_condition":"Obstacle","activation":"Activate"},{"x":59.86883762287183,"y":125.76751196685974,"width":20,"height":20,"activation_condition":"Obstacle","activation":"PreventActivate"},{"x":940.208265387401,"y":8.271767952275894,"width":20,"height":20,"activation_condition":"Obstacle","activation":"Activate"}],"action":"Jump"},{"neurones":[{"x":54.03377861894819,"y":70.73824365166405,"width":20,"height":20,"activation_condition":"Obstacle","activation":"Activate"},{"x":1200.737871303101,"y":105.22901191562475,"width":20,"height":20,"activation_condition":"Air","activation":"PreventActivate"}],"action":"Bend"}]},{"neurone_web":[{"neurones":[{"x":223.33694717139224,"y":18.73896354011049,"width":20,"height":20,"activation_condition":"Obstacle","activation":"Activate"},{"x":115.41518468067044,"y":123.89484875459036,"width":20,"height":20,"activation_condition":"Obstacle","activation":"PreventActivate"},{"x":904.6475655217023,"y":31.42838533414942,"width":20,"height":20,"activation_condition":"Obstacle","activation":"Activate"}],"action":"Jump"},{"neurones":[{"x":50.160488142195156,"y":50.59131020754867,"width":20,"height":20,"activation_condition":"Obstacle","activation":"Activate"},{"x":1198.683127567507,"y":90.7409987627528,"width":20,"height":20,"activation_condition":"Air","activation":"PreventActivate"}],"action":"Bend"}]},{"neurone_web":[{"neurones":[{"x":252.72885949991988,"y":25.40897883016239,"width":20,"height":20,"activation_condition":"Obstacle","activation":"Activate"},{"x":109.5140728143533,"y":148.20775231786146,"width":20,"height":20,"activation_condition":"Obstacle","activation":"PreventActivate"},{"x":896.2974145260355,"y":39.203408742156434,"width":20,"height":20,"activation_condition":"Obstacle","activation":"Activate"},{"x":799.5495038307238,"y":219.66690398286727,"width":20,"height":20,"activation_condition":"Obstacle","activation":"Activate"},{"x":689.3659693625951,"y":242.7948481133626,"width":20,"height":20,"activation_condition":"Obstacle","activation":"PreventActivate"}],"action":"Jump"},{"neurones":[{"x":22.402872065316686,"y":59.15346052867517,"width":20,"height":20,"activation_condition":"Obstacle","activation":"Activate"},{"x":1193.6831362926334,"y":122.3489882066612,"width":20,"height":20,"activation_condition":"Air","activation":"PreventActivate"},{"x":904.4676150460597,"y":78.10553293705458,"width":20,"height":20,"activation_condition":"Obstacle","activation":"PreventActivate"},{"x":861.824157679479,"y":568.6883419555193,"width":20,"height":20,"activation_condition":"Obstacle","activation":"Activate"}],"action":"Bend"},{"neurones":[{"x":841.999954643713,"y":473.3645825610555,"width":20,"height":20,"activation_condition":"Obstacle","activation":"PreventActivate"},{"x":1008.2129820623848,"y":472.37925892421725,"width":20,"height":20,"activation_condition":"Obstacle","activation":"Activate"},{"x":1189.2469091472447,"y":209.26685494789083,"width":20,"height":20,"activation_condition":"Air","activation":"PreventActivate"}],"action":"Unbend"}]},{"neurone_web":[{"neurones":[{"x":226.3845213270979,"y":33.19444720654668,"width":20,"height":20,"activation_condition":"Obstacle","activation":"Activate"},{"x":68.19744032130734,"y":130.0182262738642,"width":20,"height":20,"activation_condition":"Obstacle","activation":"PreventActivate"},{"x":901.2598083417022,"y":30.078069556648437,"width":20,"height":20,"activation_condition":"Obstacle","activation":"Activate"}],"action":"Jump"},{"neurones":[{"x":50.83568474117724,"y":44.948413879241045,"width":20,"height":20,"activation_condition":"Obstacle","activation":"Activate"},{"x":1198.2220182388905,"y":143.99318290291694,"width":20,"height":20,"activation_condition":"Air","activation":"PreventActivate"},{"x":483.63456615218587,"y":555.1927064984908,"width":20,"height":20,"activation_condition":"Obstacle","activation":"PreventActivate"},{"x":1208.6504778863925,"y":34.81096613325117,"width":20,"height":20,"activation_condition":"Obstacle","activation":"Activate"}],"action":"Bend"}]},{"neurone_web":[{"neurones":[{"x":235.7148108652865,"y":34.41835628624006,"width":20,"height":20,"activation_condition":"Obstacle","activation":"Activate"},{"x":48.17391908052218,"y":113.55670005095857,"width":20,"height":20,"activation_condition":"Obstacle","activation":"PreventActivate"},{"x":908.4663814179457,"y":17.083000815180114,"width":20,"height":20,"activation_condition":"Obstacle","activation":"Activate"}],"action":"Jump"},{"neurones":[{"x":1202.4784351080323,"y":133.07939343362804,"width":20,"height":20,"activation_condition":"Air","activation":"PreventActivate"},{"x":53.91940416503527,"y":92.35882014219825,"width":20,"height":20,"activation_condition":"Obstacle","activation":"Activate"},{"x":144.94499409773096,"y":483.20894107093926,"width":20,"height":20,"activation_condition":"Obstacle","activation":"Activate"}],"action":"Bend"}]},{"neurone_web":[{"neurones":[{"x":238.71054421578953,"y":7.222252394850017,"width":20,"height":20,"activation_condition":"Obstacle","activation":"Activate"},{"x":77.72082357437303,"y":100.0554088440246,"width":20,"height":20,"activation_condition":"Obstacle","activation":"PreventActivate"},{"x":901.4199005391487,"y":37.19644215954102,"width":20,"height":20,"activation_condition":"Obstacle","activation":"Activate"}],"action":"Jump"},{"neurones":[{"x":39.954405886285244,"y":66.84874022305638,"width":20,"height":20,"activation_condition":"Obstacle","activation":"Activate"},{"x":1190.6248905398686,"y":141.61266884537923,"width":20,"height":20,"activation_condition":"Air","activation":"PreventActivate"},{"x":946.5308870093396,"y":542.991370464053,"width":20,"height":20,"activation_condition":"Obstacle","activation":"Activate"}],"action":"Bend"},{"neurones":[{"x":787.8082892392193,"y":537.5353360082528,"width":20,"height":20,"activation_condition":"Air","activation":"Activate"},{"x":526.0250944261524,"y":454.68720886630103,"width":20,"height":20,"activation_condition":"Obstacle","activation":"Activate"},{"x":1179.8036113349795,"y":351.776883292955,"width":20,"height":20,"activation_condition":"Air","activation":"PreventActivate"}],"action":"Bend"}]},{"neurone_web":[{"neurones":[{"x":226.28451909872518,"y":27.142031532248282,"width":20,"height":20,"activation_condition":"Obstacle","activation":"Activate"},{"x":49.996040699156914,"y":126.52310124925906,"width":20,"height":20,"activation_condition":"Obstacle","activation":"PreventActivate"},{"x":897.9132488835045,"y":14.284296255668034,"width":20,"height":20,"activation_condition":"Obstacle","activation":"Activate"},{"x":154.7759728190128,"y":517.7197164837683,"width":20,"height":20,"activation_condition":"Obstacle","activation":"Activate"}],"action":"Jump"},{"neurones":[{"x":1193.7609399203047,"y":124.08560301771908,"width":20,"height":20,"activation_condition":"Air","activation":"PreventActivate"},{"x":753.2029979656124,"y":105.38766604415109,"width":20,"height":20,"activation_condition":"Obstacle","activation":"Activate"}],"action":"Bend"},{"neurones":[{"x":375.05404303696105,"y":519.6693518423108,"width":20,"height":20,"activation_condition":"Air","activation":"PreventActivate"},{"x":438.0661438611141,"y":568.8554966786568,"width":20,"height":20,"activation_condition":"Obstacle","activation":"Activate"}],"action":"Unbend"},{"neurones":[{"x":778.5475164246977,"y":661.7818088492005,"width":20,"height":20,"activation_condition":"Obstacle","activation":"PreventActivate"},{"x":171.19904063711306,"y":466.5423246799377,"width":20,"height":20,"activation_condition":"Air","activation":"PreventActivate"}],"action":"Unbend"},{"neurones":[{"x":653.9442700821953,"y":469.62335801349826,"width":20,"height":20,"activation_condition":"Air","activation":"Activate"},{"x":66.20549445586764,"y":593.9479160855009,"width":20,"height":20,"activation_condition":"Obstacle","activation":"Activate"},{"x":925.2399262799571,"y":439.83731342236763,"width":20,"height":20,"activation_condition":"Obstacle","activation":"Activate"},{"x":1191.1751789172358,"y":280.19777392424686,"width":20,"height":20,"activation_condition":"Air","activation":"PreventActivate"}],"action":"Jump"}]},{"neurone_web":[{"neurones":[{"x":253.8826266608406,"y":25.793134792497373,"width":20,"height":20,"activation_condition":"Obstacle","activation":"Activate"},{"x":101.7830787504266,"y":145.25377803622467,"width":20,"height":20,"activation_condition":"Obstacle","activation":"PreventActivate"},{"x":900.203834886867,"y":21.66188064911844,"width":20,"height":20,"activation_condition":"Obstacle","activation":"Activate"}],"action":"Jump"},{"neurones":[{"x":1241.949462060018,"y":98.58250113241633,"width":20,"height":20,"activation_condition":"Air","activation":"PreventActivate"},{"x":14.268358655856284,"y":51.58537482060674,"width":20,"height":20,"activation_condition":"Obstacle","activation":"Activate"}],"action":"Bend"}]},{"neurone_web":[{"neurones":[{"x":224.71275055516122,"y":31.35909144118226,"width":20,"height":20,"activation_condition":"Obstacle","activation":"Activate"},{"x":55.46120278545339,"y":135.5462625659041,"width":20,"height":20,"activation_condition":"Obstacle","activation":"PreventActivate"},{"x":893.2447246509379,"y":9.00393310407653,"width":20,"height":20,"activation_condition":"Obstacle","activation":"Activate"}],"action":"Jump"},{"neurones":[{"x":4.091424074575229,"y":22.744665855793436,"width":20,"height":20,"activation_condition":"Obstacle","activation":"Activate"},{"x":1129.991197947428,"y":112.50806594911077,"width":20,"height":20,"activation_condition":"Air","activation":"PreventActivate"},{"x":940.4325240016127,"y":343.31497795965504,"width":20,"height":20,"activation_condition":"Obstacle","activation":"PreventActivate"}],"action":"Bend"},{"neurones":[{"x":818.7661030776954,"y":467.0973039167055,"width":20,"height":20,"activation_condition":"Obstacle","activation":"PreventActivate"},{"x":866.8419121383253,"y":182.97109060567493,"width":20,"height":20,"activation_condition":"Air","activation":"Activate"},{"x":73.3352080300262,"y":423.5806711222466,"width":20,"height":20,"activation_condition":"Air","activation":"PreventActivate"}],"action":"Unbend"},{"neurones":[{"x":604.8478152592991,"y":509.3183631071755,"width":20,"height":20,"activation_condition":"Obstacle","activation":"PreventActivate"},{"x":964.0338395361492,"y":556.0466084215392,"width":20,"height":20,"activation_condition":"Obstacle","activation":"PreventActivate"},{"x":173.86225954351758,"y":221.0885432986185,"width":20,"height":20,"activation_condition":"Obstacle","activation":"Activate"},{"x":1192.7965569044445,"y":480.8857295654331,"width":20,"height":20,"activation_condition":"Obstacle","activation":"Activate"}],"action":"Bend"}]},{"neurone_web":[{"neurones":[{"x":47.996079419169526,"y":115.86933091572591,"width":20,"height":20,"activation_condition":"Obstacle","activation":"PreventActivate"},{"x":943.8869718268315,"y":23.690073845217878,"width":20,"height":20,"activation_condition":"Obstacle","activation":"Activate"},{"x":178.31024407657208,"y":38.35621444734872,"width":20,"height":20,"activation_condition":"Obstacle","activation":"Activate"},{"x":1249.276542033654,"y":599.8038816536259,"width":20,"height":20,"activation_condition":"Obstacle","activation":"PreventActivate"}],"action":"Jump"},{"neurones":[{"x":47.88735921826252,"y":83.33337513772793,"width":20,"height":20,"activation_condition":"Obstacle","activation":"Activate"},{"x":1181.855937683643,"y":120.58471921567964,"width":20,"height":20,"activation_condition":"Air","activation":"PreventActivate"},{"x":566.5008065381345,"y":370.71198623521354,"width":20,"height":20,"activation_condition":"Obstacle","activation":"PreventActivate"}],"action":"Bend"}]},{"neurone_web":[{"neurones":[{"x":190.04812188815976,"y":28.656878128443825,"width":20,"height":20,"activation_condition":"Obstacle","activation":"Activate"},{"x":61.6603876474293,"y":120.46613457420712,"width":20,"height":20,"activation_condition":"Obstacle","activation":"PreventActivate"},{"x":891.6701399887866,"y":39.1625147757125,"width":20,"height":20,"activation_condition":"Obstacle","activation":"Activate"},{"x":544.2173418385946,"y":414.64640473158926,"width":20,"height":20,"activation_condition":"Obstacle","activation":"PreventActivate"}],"action":"Jump"},{"neurones":[{"x":41.16584598075787,"y":23.181151220650797,"width":20,"height":20,"activation_condition":"Obstacle","activation":"Activate"},{"x":1177.5189283569648,"y":112.2588433810508,"width":20,"height":20,"activation_condition":"Air","activation":"PreventActivate"}],"action":"Bend"},{"neurones":[{"x":721.2382409412827,"y":228.86966024734303,"width":20,"height":20,"activation_condition":"Obstacle","activation":"PreventActivate"},{"x":963.8550662212637,"y":392.64938716054826,"width":20,"height":20,"activation_condition":"Obstacle","activation":"PreventActivate"},{"x":535.3613532934437,"y":564.4674418069695,"width":20,"height":20,"activation_condition":"Obstacle","activation":"Activate"},{"x":235.20719852493644,"y":670.9607059565798,"width":20,"height":20,"activation_condition":"Obstacle","activation":"Activate"}],"action":"Unbend"}]},{"neurone_web":[{"neurones":[{"x":232.94145344961072,"y":7.576381647586844,"width":20,"height":20,"activation_condition":"Obstacle","activation":"Activate"},{"x":58.526461707670826,"y":144.5050146599382,"width":20,"height":20,"activation_condition":"Obstacle","activation":"PreventActivate"},{"x":903.8897558796249,"y":27.175411884707948,"width":20,"height":20,"activation_condition":"Obstacle","activation":"Activate"}],"action":"Jump"},{"neurones":[{"x":1215.5328780149569,"y":112.88214763005313,"width":20,"height":20,"activation_condition":"Air","activation":"PreventActivate"},{"x":56.61676679789792,"y":7.146691139631973,"width":20,"height":20,"activation_condition":"Obstacle","activation":"Activate"},{"x":398.5670693432178,"y":256.87117554282844,"width":20,"height":20,"activation_condition":"Obstacle","activation":"Activate"}],"action":"Bend"},{"neurones":[{"x":528.4935250953235,"y":203.6716492364309,"width":20,"height":20,"activation_condition":"Obstacle","activation":"PreventActivate"},{"x":116.13277475568678,"y":210.77620419960482,"width":20,"height":20,"activation_condition":"Air","activation":"PreventActivate"},{"x":346.232985469509,"y":519.6233733440096,"width":20,"height":20,"activation_condition":"Obstacle","activation":"Activate"},{"x":410.6027743159479,"y":530.3071962521019,"width":20,"height":20,"activation_condition":"Air","activation":"Activate"},{"x":905.7392676004732,"y":432.75468098141766,"width":20,"height":20,"activation_condition":"Obstacle","activation":"Activate"}],"action":"Jump"}]},{"neurone_web":[{"neurones":[{"x":194.52422773320004,"y":27.326486427471597,"width":20,"height":20,"activation_condition":"Obstacle","activation":"Activate"},{"x":78.98796996579293,"y":110.19589515642726,"width":20,"height":20,"activation_condition":"Obstacle","activation":"PreventActivate"},{"x":901.1385013682666,"y":36.69347519105898,"width":20,"height":20,"activation_condition":"Obstacle","activation":"Activate"},{"x":360.7095562165584,"y":201.83973606989528,"width":20,"height":20,"activation_condition":"Obstacle","activation":"Activate"}],"action":"Jump"},{"neurones":[{"x":1242.8249208273855,"y":140.18708294145367,"width":20,"height":20,"activation_condition":"Air","activation":"PreventActivate"},{"x":40.30907368546124,"y":52.0058429186571,"width":20,"height":20,"activation_condition":"Obstacle","activation":"Activate"}],"action":"Bend"}]},{"neurone_web":[{"neurones":[{"x":195.36311947797125,"y":33.121553219888135,"width":20,"height":20,"activation_condition":"Obstacle","activation":"Activate"},{"x":48.60853948390566,"y":126.24227232514227,"width":20,"height":20,"activation_condition":"Obstacle","activation":"PreventActivate"},{"x":940.3955196215413,"y":38.219478724206354,"width":20,"height":20,"activation_condition":"Obstacle","activation":"Activate"}],"action":"Jump"},{"neurones":[{"x":43.944768193644926,"y":65.85070317692364,"width":20,"height":20,"activation_condition":"Obstacle","activation":"Activate"},{"x":1236.2105079373757,"y":110.74049339097134,"width":20,"height":20,"activation_condition":"Air","activation":"PreventActivate"}],"action":"Bend"}]},{"neurone_web":[{"neurones":[{"x":151.0437720804726,"y":26.244088361513978,"width":20,"height":20,"activation_condition":"Obstacle","activation":"Activate"},{"x":55.49527814032531,"y":114.55990839816107,"width":20,"height":20,"activation_condition":"Obstacle","activation":"PreventActivate"},{"x":991.8761115803502,"y":16.77541074864358,"width":20,"height":20,"activation_condition":"Obstacle","activation":"Activate"}],"action":"Jump"},{"neurones":[{"x":62.632326222127425,"y":66.80899843410685,"width":20,"height":20,"activation_condition":"Obstacle","activation":"Activate"},{"x":1192.2390347400246,"y":144.64777549134868,"width":20,"height":20,"activation_condition":"Air","activation":"PreventActivate"}],"action":"Bend"},{"neurones":[{"x":1127.2764338439347,"y":345.2373562279351,"width":20,"height":20,"activation_condition":"Obstacle","activation":"Activate"},{"x":860.1842182196613,"y":483.5882387237036,"width":20,"height":20,"activation_condition":"Obstacle","activation":"PreventActivate"}],"action":"Bend"},{"neurones":[{"x":722.7110889724102,"y":621.6733693323127,"width":20,"height":20,"activation_condition":"Obstacle","activation":"PreventActivate"},{"x":1129.7507947524034,"y":481.88099191830213,"width":20,"height":20,"activation_condition":"Obstacle","activation":"PreventActivate"}],"action":"Jump"}]},{"neurone_web":[{"neurones":[{"x":47.84383509547121,"y":135.78214872200908,"width":20,"height":20,"activation_condition":"Obstacle","activation":"PreventActivate"},{"x":932.4674919692128,"y":39.341424109237906,"width":20,"height":20,"activation_condition":"Obstacle","activation":"Activate"},{"x":170.8561285061872,"y":12.439187269601035,"width":20,"height":20,"activation_condition":"Obstacle","activation":"Activate"}],"action":"Jump"},{"neurones":[{"x":38.16445307142159,"y":26.31895574685613,"width":20,"height":20,"activation_condition":"Obstacle","activation":"Activate"},{"x":1239.5810043970416,"y":119.96387961046213,"width":20,"height":20,"activation_condition":"Air","activation":"PreventActivate"}],"action":"Bend"},{"neurones":[{"x":432.72409174461256,"y":438.60176033858943,"width":20,"height":20,"activation_condition":"Obstacle","activation":"Activate"},{"x":874.0507674553396,"y":435.4269701809622,"width":20,"height":20,"activation_condition":"Air","activation":"PreventActivate"},{"x":58.19128373626367,"y":346.951076230717,"width":20,"height":20,"activation_condition":"Air","activation":"PreventActivate"}],"action":"Bend"},{"neurones":[{"x":1056.1063674741856,"y":532.0946780125346,"width":20,"height":20,"activation_condition":"Air","activation":"PreventActivate"},{"x":850.1874979024684,"y":471.99717141145504,"width":20,"height":20,"activation_condition":"Air","activation":"PreventActivate"},{"x":72.67197187768339,"y":178.4384094469046,"width":20,"height":20,"activation_condition":"Air","activation":"Activate"},{"x":1133.0506312422401,"y":589.5193429780019,"width":20,"height":20,"activation_condition":"Obstacle","activation":"Activate"},{"x":920.5590814278374,"y":552.3204423245878,"width":20,"height":20,"activation_condition":"Air","activation":"PreventActivate"}],"action":"Bend"}]},{"neurone_web":[{"neurones":[{"x":189.06087250577914,"y":34.61104411930375,"width":20,"height":20,"activation_condition":"Obstacle","activation":"Activate"},{"x":55.24209443935062,"y":110.51833437597195,"width":20,"height":20,"activation_condition":"Obstacle","activation":"PreventActivate"},{"x":911.8728154221014,"y":36.86557914730512,"width":20,"height":20,"activation_condition":"Obstacle","activation":"Activate"}],"action":"Jump"},{"neurones":[{"x":53.905577656582786,"y":34.02440773873143,"width":20,"height":20,"activation_condition":"Obstacle","activation":"Activate"},{"x":1227.609999675028,"y":94.23452579465052,"width":20,"height":20,"activation_condition":"Air","activation":"PreventActivate"}],"action":"Bend"},{"neurones":[{"x":543.9218084698858,"y":21.33297065323216,"width":20,"height":20,"activation_condition":"Air","activation":"PreventActivate"},{"x":1138.5137155677335,"y":354.5413741126031,"width":20,"height":20,"activation_condition":"Obstacle","activation":"Activate"},{"x":370.2315817047816,"y":621.4209429791993,"width":20,"height":20,"activation_condition":"Obstacle","activation":"PreventActivate"}],"action":"Jump"}]},{"neurone_web":[{"neurones":[{"x":185.35999952075116,"y":16.970795663180944,"width":20,"height":20,"activation_condition":"Obstacle","activation":"Activate"},{"x":64.28059178394223,"y":136.02591378718068,"width":20,"height":20,"activation_condition":"Obstacle","activation":"PreventActivate"},{"x":893.6180072914004,"y":14.838165855884021,"width":20,"height":20,"activation_condition":"Obstacle","activation":"Activate"}],"action":"Jump"},{"neurones":[{"x":1199.0165202818137,"y":116.63086709181974,"width":20,"height":20,"activation_condition":"Air","activation":"PreventActivate"},{"x":61.007105079574224,"y":96.73370315109396,"width":20,"height":20,"activation_condition":"Obstacle","activation":"Activate"},{"x":160.93416184609526,"y":537.7072684773416,"width":20,"height":20,"activation_condition":"Obstacle","activation":"Activate"}],"action":"Bend"},{"neurones":[{"x":836.1822013048569,"y":266.8469247717471,"width":20,"height":20,"activation_condition":"Air","activation":"Activate"},{"x":62.825664083041545,"y":620.9684537851709,"width":20,"height":20,"activation_condition":"Air","activation":"PreventActivate"}],"action":"Bend"}]},{"neurone_web":[{"neurones":[{"x":223.03376516235588,"y":29.07779126490379,"width":20,"height":20,"activation_condition":"Obstacle","activation":"Activate"},{"x":100.46630693744856,"y":90.79086163259012,"width":20,"height":20,"activation_condition":"Obstacle","activation":"PreventActivate"},{"x":893.2959813205327,"y":25.566430503536687,"width":20,"height":20,"activation_condition":"Obstacle","activation":"Activate"}],"action":"Jump"},{"neurones":[{"x":1206.9419622415212,"y":112.27895482676462,"width":20,"height":20,"activation_condition":"Air","activation":"PreventActivate"},{"x":18.968644874842678,"y":13.151503025131781,"width":20,"height":20,"activation_condition":"Obstacle","activation":"Activate"}],"action":"Bend"}]},{"neurone_web":[{"neurones":[{"x":193.32223366315168,"y":15.001840021701462,"width":20,"height":20,"activation_condition":"Obstacle","activation":"Activate"},{"x":74.71969122570101,"y":124.82217071200765,"width":20,"height":20,"activation_condition":"Obstacle","activation":"PreventActivate"},{"x":896.0653896874154,"y":38.120498526515775,"width":20,"height":20,"activation_condition":"Obstacle","activation":"Activate"}],"action":"Jump"},{"neurones":[{"x":1259.7924998439569,"y":106.66187778791885,"width":20,"height":20,"activation_condition":"Air","activation":"PreventActivate"},{"x":84.44323116791571,"y":63.52145003447228,"width":20,"height":20,"activation_condition":"Obstacle","activation":"Activate"}],"action":"Bend"},{"neurones":[{"x":213.81800426317724,"y":374.4241860538961,"width":20,"height":20,"activation_condition":"Obstacle","activation":"Activate"}],"action":"Jump"}]},{"neurone_web":[{"neurones":[{"x":207.95577636596107,"y":11.717801271183191,"width":20,"height":20,"activation_condition":"Obstacle","activation":"Activate"},{"x":47.25179648632743,"y":133.90638073277037,"width":20,"height":20,"activation_condition":"Obstacle","activation":"PreventActivate"},{"x":916.7001193467772,"y":27.601767484333074,"width":20,"height":20,"activation_condition":"Obstacle","activation":"Activate"}],"action":"Jump"},{"neurones":[{"x":1220.4680566885907,"y":105.63432164339369,"width":20,"height":20,"activation_condition":"Air","activation":"PreventActivate"},{"x":46.633649644174696,"y":88.78167573369329,"width":20,"height":20,"activation_condition":"Obstacle","activation":"Activate"},{"x":202.07326551318198,"y":535.592057635605,"width":20,"height":20,"activation_condition":"Obstacle","activation":"Activate"}],"action":"Bend"}]},{"neurone_web":[{"neurones":[{"x":246.70258435897117,"y":21.610237736992133,"width":20,"height":20,"activation_condition":"Obstacle","activation":"Activate"},{"x":63.17486886691355,"y":122.55202419778232,"width":20,"height":20,"activation_condition":"Obstacle","activation":"PreventActivate"},{"x":896.3429979946358,"y":20.677049023001018,"width":20,"height":20,"activation_condition":"Obstacle","activation":"Activate"}],"action":"Jump"},{"neurones":[{"x":22.50525771620682,"y":46.91369050252223,"width":20,"height":20,"activation_condition":"Obstacle","activation":"Activate"},{"x":1167.4527110819377,"y":93.6517663588526,"width":20,"height":20,"activation_condition":"Air","activation":"PreventActivate"}],"action":"Bend"}]},{"neurone_web":[{"neurones":[{"x":186.36832621227873,"y":26.954518320173612,"width":20,"height":20,"activation_condition":"Obstacle","activation":"Activate"},{"x":47.95372555646322,"y":129.5309977092881,"width":20,"height":20,"activation_condition":"Obstacle","activation":"PreventActivate"},{"x":928.8362928200803,"y":23.810686875948118,"width":20,"height":20,"activation_condition":"Obstacle","activation":"Activate"}],"action":"Jump"},{"neurones":[{"x":8.165761953836643,"y":44.48401993971009,"width":20,"height":20,"activation_condition":"Obstacle","activation":"Activate"},{"x":1139.767393325199,"y":113.70111396832964,"width":20,"height":20,"activation_condition":"Air","activation":"PreventActivate"},{"x":904.7810868842123,"y":322.970831924011,"width":20,"height":20,"activation_condition":"Obstacle","activation":"PreventActivate"}],"action":"Bend"},{"neurones":[{"x":602.5698167306311,"y":487.0648109102455,"width":20,"height":20,"activation_condition":"Obstacle","activation":"PreventActivate"},{"x":990.9683255443056,"y":561.2684052411761,"width":20,"height":20,"activation_condition":"Obstacle","activation":"PreventActivate"},{"x":147.98911528560015,"y":197.60621502080187,"width":20,"height":20,"activation_condition":"Obstacle","activation":"Activate"},{"x":1254.5448746229172,"y":180.58678793637398,"width":20,"height":20,"activation_condition":"Obstacle","activation":"Activate"}],"action":"Bend"}]},{"neurone_web":[{"neurones":[{"x":236.82715739130467,"y":27.749777118489646,"width":20,"height":20,"activation_condition":"Obstacle","activation":"Activate"},{"x":62.33158906880135,"y":117.95402186988791,"width":20,"height":20,"activation_condition":"Obstacle","activation":"PreventActivate"},{"x":898.9430759988318,"y":23.995834994934643,"width":20,"height":20,"activation_condition":"Obstacle","activation":"Activate"}],"action":"Jump"},{"neurones":[{"x":1200.5995051199761,"y":95.9562731811844,"width":20,"height":20,"activation_condition":"Air","activation":"PreventActivate"},{"x":46.69065015270534,"y":92.52797934648697,"width":20,"height":20,"activation_condition":"Obstacle","activation":"Activate"},{"x":239.06776416844076,"y":505.08513658381196,"width":20,"height":20,"activation_condition":"Obstacle","activation":"Activate"}],"action":"Bend"},{"neurones":[{"x":301.45832648446293,"y":289.5003283324471,"width":20,"height":20,"activation_condition":"Air","activation":"PreventActivate"},{"x":365.89267103636496,"y":19.72739889181735,"width":20,"height":20,"activation_condition":"Obstacle","activation":"Activate"},{"x":736.9307156859904,"y":428.3336555094103,"width":20,"height":20,"activation_condition":"Air","activation":"PreventActivate"},{"x":91.25159809235636,"y":696.2983990899613,"width":20,"height":20,"activation_condition":"Obstacle","activation":"Activate"}],"action":"Bend"}]},{"neurone_web":[{"neurones":[{"x":216.30846001143635,"y":7.718517667509599,"width":20,"height":20,"activation_condition":"Obstacle","activation":"Activate"},{"x":90.21145946756437,"y":118.25880846555229,"width":20,"height":20,"activation_condition":"Obstacle","activation":"PreventActivate"},{"x":902.7289634264793,"y":10.92227789474792,"width":20,"height":20,"activation_condition":"Obstacle","activation":"Activate"}],"action":"Jump"},{"neurones":[{"x":126.15823012837596,"y":28.03835328495174,"width":20,"height":20,"activation_condition":"Obstacle","activation":"Activate"},{"x":1255.5243117860582,"y":134.77682148597899,"width":20,"height":20,"activation_condition":"Air","activation":"PreventActivate"},{"x":92.25798711026984,"y":615.925497250317,"width":20,"height":20,"activation_condition":"Obstacle","activation":"PreventActivate"}],"action":"Bend"},{"neurones":[{"x":211.00665716810076,"y":167.63786350772835,"width":20,"height":20,"activation_condition":"Air","activation":"PreventActivate"},{"x":320.6402029035861,"y":325.6543908554737,"width":20,"height":20,"activation_condition":"Air","activation":"Activate"},{"x":913.710202110245,"y":278.57443089450436,"width":20,"height":20,"activation_condition":"Obstacle","activation":"PreventActivate"},{"x":298.2669591627279,"y":45.29882234823528,"width":20,"height":20,"activation_condition":"Obstacle","activation":"PreventActivate"},{"x":762.8778656908779,"y":375.1617121813886,"width":20,"height":20,"activation_condition":"Air","activation":"Activate"}],"action":"Bend"}]},{"neurone_web":[{"neurones":[{"x":79.28671224280987,"y":126.12492705433593,"width":20,"height":20,"activation_condition":"Obstacle","activation":"PreventActivate"},{"x":903.3631082566254,"y":23.544113466625284,"width":20,"height":20,"activation_condition":"Obstacle","activation":"Activate"},{"x":240.1628780577211,"y":39.6908341609278,"width":20,"height":20,"activation_condition":"Obstacle","activation":"Activate"},{"x":125.70123595961319,"y":477.58880443798944,"width":20,"height":20,"activation_condition":"Obstacle","activation":"Activate"}],"action":"Jump"},{"neurones":[{"x":65.61196010288873,"y":35.8398529489108,"width":20,"height":20,"activation_condition":"Obstacle","activation":"Activate"},{"x":1212.0407437413378,"y":144.1172365359383,"width":20,"height":20,"activation_condition":"Air","activation":"PreventActivate"}],"action":"Bend"},{"neurones":[{"x":203.99980358270747,"y":340.169772347578,"width":20,"height":20,"activation_condition":"Obstacle","activation":"Activate"},{"x":745.8578495765238,"y":572.5842154836529,"width":20,"height":20,"activation_condition":"Air","activation":"Activate"},{"x":258.1176787217498,"y":442.7885148567207,"width":20,"height":20,"activation_condition":"Air","activation":"PreventActivate"},{"x":501.4952308946281,"y":607.2528520169835,"width":20,"height":20,"activation_condition":"Obstacle","activation":"PreventActivate"},{"x":180.54065400735394,"y":519.8130257166301,"width":20,"height":20,"activation_condition":"Air","activation":"Activate"}],"action":"Unbend"}]},{"neurone_web":[{"neurones":[{"x":223.72037882918698,"y":25.105715311171835,"width":20,"height":20,"activation_condition":"Obstacle","activation":"Activate"},{"x":89.01525650342862,"y":126.87653822979144,"width":20,"height":20,"activation_condition":"Obstacle","activation":"PreventActivate"},{"x":896.1571761229378,"y":39.94370703256317,"width":20,"height":20,"activation_condition":"Obstacle","activation":"Activate"}],"action":"Jump"},{"neurones":[{"x":65.51221809844962,"y":48.603303244627355,"width":20,"height":20,"activation_condition":"Obstacle","activation":"Activate"},{"x":1216.5310783788652,"y":116.54462692392106,"width":20,"height":20,"activation_condition":"Air","activation":"PreventActivate"}],"action":"Bend"}]},{"neurone_web":[{"neurones":[{"x":212.62451160365157,"y":16.078640071767186,"width":20,"height":20,"activation_condition":"Obstacle","activation":"Activate"},{"x":53.12699638883741,"y":125.22915392890155,"width":20,"height":20,"activation_condition":"Obstacle","activation":"PreventActivate"},{"x":912.2547625509177,"y":22.265411138855494,"width":20,"height":20,"activation_condition":"Obstacle","activation":"Activate"}],"action":"Jump"},{"neurones":[{"x":12.124108352983948,"y":66.63299545387757,"width":20,"height":20,"activation_condition":"Obstacle","activation":"Activate"},{"x":1192.0499527129584,"y":130.62036257837366,"width":20,"height":20,"activation_condition":"Air","activation":"PreventActivate"}],"action":"Bend"}]},{"neurone_web":[{"neurones":[{"x":237.81205052917085,"y":37.954906143996,"width":20,"height":20,"activation_condition":"Obstacle","activation":"Activate"},{"x":123.3393888738935,"y":108.37002269725724,"width":20,"height":20,"activation_condition":"Obstacle","activation":"PreventActivate"},{"x":892.4316641838791,"y":14.369677614399087,"width":20,"height":20,"activation_condition":"Obstacle","activation":"Activate"},{"x":466.8518498151759,"y":551.059371440871,"width":20,"height":20,"activation_condition":"Obstacle","activation":"PreventActivate"}],"action":"Jump"},{"neurones":[{"x":1244.6876216311373,"y":129.48872763884253,"width":20,"height":20,"activation_condition":"Air","activation":"PreventActivate"},{"x":95.74732285507494,"y":47.57039317828027,"width":20,"height":20,"activation_condition":"Obstacle","activation":"Activate"}],"action":"Bend"},{"neurones":[{"x":969.827216076251,"y":109.70322904723142,"width":20,"height":20,"activation_condition":"Air","activation":"Activate"},{"x":1064.635546115244,"y":371.3598888040442,"width":20,"height":20,"activation_condition":"Obstacle","activation":"Activate"},{"x":630.5035993015296,"y":300.87364361093233,"width":20,"height":20,"activation_condition":"Air","activation":"PreventActivate"},{"x":301.5098642629593,"y":458.4390897637178,"width":20,"height":20,"activation_condition":"Obstacle","activation":"Activate"},{"x":700.2925890946437,"y":648.3659944716661,"width":20,"height":20,"activation_condition":"Obstacle","activation":"PreventActivate"}],"action":"Bend"}]}],"rng":{"state":260854768077960096945939413191812539103,"increment":1},"score":9}